<?xml version="1.0" encoding="UTF-8"?>
 <xml> 
   <Geometry type="TensorBSpline2" id="0"> 
   <Basis type="TensorBSplineBasis2"> 
     <Basis type="BSplineBasis" index="0"> 
<KnotVector degree="3">  0.    0.    0.    0.    0.05  0.1   0.15  0.2   0.25  0.3   0.35  0.4
  0.45  0.5   0.55  0.6   0.65  0.7   0.75  0.8   0.85  0.9   0.95  1.    1.
  1.    1.   </KnotVector> 
     </Basis> 
     <Basis type="BSplineBasis" index="1"> 
<KnotVector degree="3">  0.     0.     0.     0.     0.025  0.05   0.075  0.1    0.125  0.15
  0.175  0.2    0.225  0.25   0.275  0.3    0.325  0.35   0.375  0.4    0.425
  0.45   0.475  0.5    0.525  0.55   0.575  0.6    0.625  0.65   0.675  0.7
  0.725  0.75   0.775  0.8    0.825  0.85   0.875  0.9    0.925  0.95
  0.975  1.     1.     1.     1.    </KnotVector> 
     </Basis> 
    </Basis> 
    <coefs geoDim="2"> 
 -2.30782278e-01  -9.17480017e+00
  -1.19269675e-01  -9.18597942e+00
   1.05404401e-01  -9.19220807e+00
   4.40131076e-01  -9.15216291e+00
   7.65806628e-01  -9.06550543e+00
   1.07735144e+00  -8.93736011e+00
   1.37175685e+00  -8.77391960e+00
   1.64777316e+00  -8.58124306e+00
   1.90533844e+00  -8.36466143e+00
   2.14510820e+00  -8.12862916e+00
   2.36805272e+00  -7.87671064e+00
   2.57527536e+00  -7.61175678e+00
   2.76786717e+00  -7.33601806e+00
   2.94686799e+00  -7.05129349e+00
   3.11321905e+00  -6.75901545e+00
   3.26776864e+00  -6.46034273e+00
   3.41127499e+00  -6.15621970e+00
   3.54440315e+00  -5.84742085e+00
   3.66774871e+00  -5.53459168e+00
   3.78182332e+00  -5.21826944e+00
   3.88709966e+00  -4.89891445e+00
   3.95165795e+00  -4.68424080e+00
   3.98263044e+00  -4.57652914e+00
  -1.87415655e-01  -9.04831815e+00
  -6.52386166e-02  -9.05785545e+00
   1.66413368e-01  -9.05680405e+00
   4.99539672e-01  -9.00468905e+00
   8.20541779e-01  -8.90812813e+00
   1.12565660e+00  -8.77265021e+00
   1.41356865e+00  -8.60434617e+00
   1.68330238e+00  -8.40861519e+00
   1.93500359e+00  -8.19031469e+00
   2.16918532e+00  -7.95345116e+00
   2.38670559e+00  -7.70131479e+00
   2.58849014e+00  -7.43656388e+00
   2.77548578e+00  -7.16137108e+00
   2.94866621e+00  -6.87753405e+00
   3.10902740e+00  -6.58653440e+00
   3.25755194e+00  -6.28963368e+00
   3.39514323e+00  -5.98786375e+00
   3.52256837e+00  -5.68227078e+00
   3.64049191e+00  -5.37366200e+00
   3.74955112e+00  -5.06249081e+00
   3.85028330e+00  -4.74941988e+00
   3.91084435e+00  -4.54628149e+00
   3.93401368e+00  -4.47516274e+00
  -5.95468226e-02  -8.81905809e+00
   6.58071104e-02  -8.82026174e+00
   2.93832796e-01  -8.79956671e+00
   6.20765985e-01  -8.72321773e+00
   9.29609850e-01  -8.60727630e+00
   1.22240870e+00  -8.45784471e+00
   1.49769555e+00  -8.27955061e+00
   1.75513750e+00  -8.07704115e+00
   1.99482217e+00  -7.85429690e+00
   2.21722670e+00  -7.61467729e+00
   2.42283813e+00  -7.36100304e+00
   2.61222423e+00  -7.09572129e+00
   2.78629115e+00  -6.82100295e+00
   2.94628631e+00  -6.53872852e+00
   3.09361833e+00  -6.25052576e+00
   3.22962287e+00  -5.95775751e+00
   3.35541377e+00  -5.66169860e+00
   3.47186932e+00  -5.36351740e+00
   3.57959639e+00  -5.06466677e+00
   3.67833717e+00  -4.77037991e+00
   3.76601885e+00  -4.49412983e+00
   3.81215805e+00  -4.35122889e+00
   3.83588399e+00  -4.27278145e+00
   1.70467682e-01  -8.49389183e+00
   2.76931356e-01  -8.47550896e+00
   4.93636808e-01  -8.42734174e+00
   7.99276588e-01  -8.31892510e+00
   1.09036882e+00  -8.17883762e+00
   1.36435361e+00  -8.01050109e+00
   1.62020150e+00  -7.81797410e+00
   1.85795742e+00  -7.60491280e+00
   2.07744935e+00  -7.37442674e+00
   2.27851653e+00  -7.12939505e+00
   2.46153056e+00  -6.87256790e+00
   2.62784177e+00  -6.60652854e+00
   2.77943745e+00  -6.33354242e+00
   2.91840586e+00  -6.05555120e+00
   3.04652245e+00  -5.77425678e+00
   3.16509844e+00  -5.49136971e+00
   3.27498636e+00  -5.20896625e+00
   3.37658930e+00  -4.93011782e+00
   3.46965659e+00  -4.66083118e+00
   3.55368112e+00  -4.40879853e+00
   3.62841240e+00  -4.18341314e+00
   3.67701340e+00  -4.03358542e+00
   3.70053538e+00  -3.96379760e+00
   3.72675840e-01  -8.15444861e+00
   4.81341719e-01  -8.12643353e+00
   6.82066654e-01  -8.05749025e+00
   9.72629281e-01  -7.92416964e+00
   1.24509387e+00  -7.76295163e+00
   1.49846674e+00  -7.57787917e+00
   1.73344778e+00  -7.37224402e+00
   1.94866890e+00  -7.14880861e+00
   2.14306712e+00  -6.91058249e+00
   2.31726050e+00  -6.66074826e+00
   2.47369370e+00  -6.40231979e+00
   2.61547089e+00  -6.13784789e+00
   2.74537192e+00  -5.86945037e+00
   2.86543412e+00  -5.59902154e+00
   2.97697803e+00  -5.32853555e+00
   3.08078261e+00  -5.06039680e+00
   3.17725594e+00  -4.79770420e+00
   3.26654068e+00  -4.54468636e+00
   3.34906051e+00  -4.30458001e+00
   3.42580264e+00  -4.07895712e+00
   3.49981330e+00  -3.85892128e+00
   3.54660633e+00  -3.72176896e+00
   3.56968401e+00  -3.65291086e+00
   5.80435972e-01  -7.81455300e+00
   6.72507603e-01  -7.77542379e+00
   8.68175797e-01  -7.68986853e+00
   1.13843689e+00  -7.53357538e+00
   1.38854857e+00  -7.35420275e+00
   1.62093337e+00  -7.15438070e+00
   1.83073247e+00  -6.93622554e+00
   2.01581622e+00  -6.70315978e+00
   2.17823680e+00  -6.45902866e+00
   2.32259467e+00  -6.20727022e+00
   2.45339637e+00  -5.95055296e+00
   2.57388657e+00  -5.69099013e+00
   2.68604286e+00  -5.43048543e+00
   2.79098923e+00  -5.17101869e+00
   2.88937736e+00  -4.91483173e+00
   2.98164266e+00  -4.66438014e+00
   3.06817680e+00  -4.42217825e+00
   3.14964866e+00  -4.18943725e+00
   3.22696398e+00  -3.96626329e+00
   3.30147145e+00  -3.74964669e+00
   3.37296161e+00  -3.54274274e+00
   3.41959014e+00  -3.40697164e+00
   3.44269738e+00  -3.34041722e+00
   7.63495363e-01  -7.46641431e+00
   8.66113368e-01  -7.42155212e+00
   1.04231581e+00  -7.31942201e+00
   1.28917349e+00  -7.14489803e+00
   1.52117689e+00  -6.94983117e+00
   1.72390293e+00  -6.73526444e+00
   1.89553542e+00  -6.50577924e+00
   2.04246994e+00  -6.26621674e+00
   2.17270694e+00  -6.02030010e+00
   2.29192047e+00  -5.77055832e+00
   2.40316028e+00  -5.51891091e+00
   2.50789252e+00  -5.26712363e+00
   2.60685226e+00  -5.01700026e+00
   2.70050642e+00  -4.77040757e+00
   2.78925613e+00  -4.52910839e+00
   2.87354390e+00  -4.29454710e+00
   2.95397711e+00  -4.06723300e+00
   3.03121539e+00  -3.84716432e+00
   3.10599723e+00  -3.63326308e+00
   3.17854510e+00  -3.42639094e+00
   3.24985253e+00  -3.22329716e+00
   3.29663503e+00  -3.09160338e+00
   3.31987600e+00  -3.02626589e+00
   9.62514918e-01  -7.11687709e+00
   1.03472162e+00  -7.06146489e+00
   1.19982018e+00  -6.94859340e+00
   1.43720421e+00  -6.75757329e+00
   1.62830901e+00  -6.54459720e+00
   1.77941115e+00  -6.31709981e+00
   1.90666710e+00  -6.08117675e+00
   2.02161357e+00  -5.84038755e+00
   2.12960716e+00  -5.59679933e+00
   2.23237556e+00  -5.35201530e+00
   2.33046360e+00  -5.10760922e+00
   2.42414399e+00  -4.86514546e+00
   2.51369284e+00  -4.62610376e+00
   2.59943011e+00  -4.39172362e+00
   2.68174139e+00  -4.16288096e+00
   2.76110292e+00  -3.93987261e+00
   2.83799722e+00  -3.72273023e+00
   2.91293171e+00  -3.51097288e+00
   2.98625184e+00  -3.30465533e+00
   3.05858790e+00  -3.10220762e+00
   3.13006934e+00  -2.90445962e+00
   3.17742079e+00  -2.77481793e+00
   3.20109985e+00  -2.71056220e+00
   1.10843218e+00  -6.75793588e+00
   1.20684174e+00  -6.70202898e+00
   1.37591727e+00  -6.57695309e+00
   1.54150620e+00  -6.36268084e+00
   1.66120176e+00  -6.13568450e+00
   1.76604051e+00  -5.90283641e+00
   1.86676832e+00  -5.66656484e+00
   1.96525590e+00  -5.42824143e+00
   2.06087429e+00  -5.18918947e+00
   2.15326146e+00  -4.95083280e+00
   2.24238228e+00  -4.71450649e+00
   2.32838440e+00  -4.48136715e+00
   2.41149859e+00  -4.25230361e+00
   2.49202281e+00  -4.02789729e+00
   2.57031791e+00  -3.80836872e+00
   2.64675535e+00  -3.59375356e+00
   2.72172771e+00  -3.38378144e+00
   2.79557102e+00  -3.17831068e+00
   2.86870814e+00  -2.97658858e+00
   2.94132686e+00  -2.77890036e+00
   3.01380612e+00  -2.58430712e+00
   3.06221614e+00  -2.45667105e+00
   3.08646316e+00  -2.39333195e+00
   1.33303520e+00  -6.40461338e+00
   1.38491561e+00  -6.33446544e+00
   1.45102380e+00  -6.18714171e+00
   1.52954832e+00  -5.96004501e+00
   1.61557831e+00  -5.73028169e+00
   1.70670943e+00  -5.49792839e+00
   1.79839614e+00  -5.26387219e+00
   1.88829611e+00  -5.02941098e+00
   1.97587490e+00  -4.79587813e+00
   2.06110399e+00  -4.56439669e+00
   2.14405355e+00  -4.33586406e+00
   2.22486997e+00  -4.11093813e+00
   2.30376954e+00  -3.89003555e+00
   2.38103161e+00  -3.67333126e+00
   2.45695635e+00  -3.46085047e+00
   2.53186294e+00  -3.25242360e+00
   2.60604662e+00  -3.04789877e+00
   2.67982521e+00  -2.84688266e+00
   2.75341775e+00  -2.64938541e+00
   2.82714042e+00  -2.45481805e+00
   2.90120601e+00  -2.26320199e+00
   2.95094108e+00  -2.13723196e+00
   2.97594513e+00  -2.07464365e+00
   1.32043267e+00  -6.01236658e+00
   1.33226437e+00  -5.93811076e+00
   1.37149311e+00  -5.78919394e+00
   1.45462875e+00  -5.56294372e+00
   1.54256368e+00  -5.33358109e+00
   1.62937727e+00  -5.10266322e+00
   1.71445848e+00  -4.87173659e+00
   1.79795750e+00  -4.64197724e+00
   1.87990751e+00  -4.41428331e+00
   1.96024541e+00  -4.18934433e+00
   2.03904026e+00  -3.96766377e+00
   2.11645634e+00  -3.74955405e+00
   2.19272573e+00  -3.53515186e+00
   2.26810340e+00  -3.32447120e+00
   2.34285856e+00  -3.11739928e+00
   2.41724954e+00  -2.91380809e+00
   2.49153971e+00  -2.71345777e+00
   2.56595129e+00  -2.51625270e+00
   2.64074476e+00  -2.32183245e+00
   2.71611177e+00  -2.13016965e+00
   2.79225715e+00  -1.94100055e+00
   2.84368352e+00  -1.81644281e+00
   2.86958683e+00  -1.75454285e+00
   1.20423696e+00  -5.62563703e+00
   1.23397820e+00  -5.55107236e+00
   1.29345899e+00  -5.40059930e+00
   1.37709252e+00  -5.17236609e+00
   1.45825473e+00  -4.94353402e+00
   1.53901331e+00  -4.71531132e+00
   1.61922756e+00  -4.48848090e+00
   1.69849583e+00  -4.26372156e+00
   1.77659469e+00  -4.04158204e+00
   1.85358286e+00  -3.82246048e+00
   1.92962619e+00  -3.60659354e+00
   2.00493590e+00  -3.39408150e+00
   2.07973904e+00  -3.18492717e+00
   2.15427134e+00  -2.97904768e+00
   2.22876452e+00  -2.77633453e+00
   2.30345041e+00  -2.57661763e+00
   2.37854143e+00  -2.37977513e+00
   2.45426022e+00  -2.18557536e+00
   2.53079040e+00  -1.99394799e+00
   2.60832839e+00  -1.80467664e+00
   2.68705918e+00  -1.61764752e+00
   2.74044554e+00  -1.49438823e+00
   2.76739316e+00  -1.43308842e+00
   1.13271735e+00  -5.23900563e+00
   1.15733377e+00  -5.16358711e+00
   1.20659240e+00  -5.01231446e+00
   1.28338829e+00  -4.78547901e+00
   1.36170843e+00  -4.55943875e+00
   1.43968595e+00  -4.33483537e+00
   1.51671869e+00  -4.11231232e+00
   1.59280205e+00  -3.89235083e+00
   1.66812012e+00  -3.67526168e+00
   1.74286709e+00  -3.46121398e+00
   1.81723687e+00  -3.25027166e+00
   1.89143660e+00  -3.04242445e+00
   1.96568099e+00  -2.83760145e+00
   2.04018445e+00  -2.63570484e+00
   2.11515905e+00  -2.43659920e+00
   2.19080499e+00  -2.24016373e+00
   2.26732139e+00  -2.04623250e+00
   2.34488573e+00  -1.85471149e+00
   2.42368069e+00  -1.66543038e+00
   2.50387348e+00  -1.47829503e+00
   2.58561926e+00  -1.29319737e+00
   2.64125969e+00  -1.17108027e+00
   2.66938984e+00  -1.11033166e+00
   1.02859219e+00  -4.85430453e+00
   1.05450117e+00  -4.77896083e+00
   1.10673539e+00  -4.62841861e+00
   1.18399118e+00  -4.40361880e+00
   1.25969463e+00  -4.18051352e+00
   1.33441097e+00  -3.95966580e+00
   1.40854324e+00  -3.74141786e+00
   1.48228973e+00  -3.52596787e+00
   1.55579641e+00  -3.31341940e+00
   1.62923029e+00  -3.10380316e+00
   1.70278915e+00  -2.89709377e+00
   1.77667957e+00  -2.69322080e+00
   1.85110625e+00  -2.49208985e+00
   1.92626861e+00  -2.29358279e+00
   2.00235626e+00  -2.09758481e+00
   2.07955348e+00  -1.90396207e+00
   2.15803101e+00  -1.71261217e+00
   2.23795851e+00  -1.52339871e+00
   2.31949238e+00  -1.33623346e+00
   2.40278330e+00  -1.15101197e+00
   2.48798111e+00  -9.67639461e-01
   2.54614275e+00  -8.46577486e-01
   2.57558728e+00  -7.86329193e-01
   9.32854810e-01  -4.47082983e+00
   9.57336705e-01  -4.39597104e+00
   1.00595652e+00  -4.24671940e+00
   1.07849851e+00  -4.02485975e+00
   1.15102013e+00  -3.80540342e+00
   1.22345651e+00  -3.58855976e+00
   1.29576568e+00  -3.37446133e+00
   1.36806023e+00  -3.16317560e+00
   1.44053213e+00  -2.95470741e+00
   1.51339649e+00  -2.74901323e+00
   1.58686119e+00  -2.54601504e+00
   1.66112483e+00  -2.34561620e+00
   1.73637789e+00  -2.14770564e+00
   1.81280159e+00  -1.95217250e+00
   1.89057015e+00  -1.75889832e+00
   1.96984740e+00  -1.56777976e+00
   2.05079259e+00  -1.37870145e+00
   2.13355447e+00  -1.19157638e+00
   2.21827765e+00  -1.00630761e+00
   2.30510255e+00  -8.22813313e-01
   2.39416203e+00  -6.41024733e-01
   2.45511347e+00  -5.20922147e-01
   2.48600566e+00  -4.61134334e-01
   8.23647725e-01  -4.08907939e+00
   8.47550572e-01  -4.01504321e+00
   8.95262487e-01  -3.86774208e+00
   9.66532152e-01  -3.64932495e+00
   1.03747588e+00  -3.43358486e+00
   1.10830058e+00  -3.22060963e+00
   1.17930417e+00  -3.01042066e+00
   1.25074647e+00  -2.80298251e+00
   1.32284935e+00  -2.59822536e+00
   1.39581239e+00  -2.39605794e+00
   1.46982646e+00  -2.19637762e+00
   1.54507545e+00  -1.99907400e+00
   1.62173452e+00  -1.80403704e+00
   1.69997059e+00  -1.61115510e+00
   1.77994112e+00  -1.42032586e+00
   1.86179709e+00  -1.23144554e+00
   1.94568094e+00  -1.04442767e+00
   2.03173075e+00  -8.59183130e-01
   2.12007940e+00  -6.75637672e-01
   2.21085480e+00  -4.93724813e-01
   2.30418400e+00  -3.13381410e-01
   2.36818858e+00  -1.94165448e-01
   2.40065747e+00  -1.34802885e-01
   7.12703555e-01  -3.70892510e+00
   7.35671653e-01  -3.63596176e+00
   7.81543589e-01  -3.49093630e+00
   8.50342617e-01  -3.27618486e+00
   9.19437515e-01  -3.06424386e+00
   9.89076257e-01  -2.85507601e+00
   1.05944389e+00  -2.64860855e+00
   1.13072393e+00  -2.44475079e+00
   1.20310660e+00  -2.24339964e+00
   1.27678229e+00  -2.04444487e+00
   1.35193327e+00  -1.84777265e+00
   1.42873068e+00  -1.65327102e+00
   1.50733560e+00  -1.46083029e+00
   1.58789950e+00  -1.27034866e+00
   1.67056650e+00  -1.08172811e+00
   1.75547315e+00  -8.94882897e-01
   1.84275115e+00  -7.09730167e-01
   1.93252710e+00  -5.26200161e-01
   2.02492385e+00  -3.44229606e-01
   2.12006264e+00  -1.63762174e-01
   2.21806231e+00   1.52477211e-02
   2.28538188e+00   1.33643213e-01
   2.31955836e+00   1.92610447e-01
   5.93778923e-01  -3.33057286e+00
   6.16151780e-01  -3.25881257e+00
   6.60952450e-01  -3.11626016e+00
   7.28620787e-01  -2.90528819e+00
   7.96974332e-01  -2.69708922e+00
   8.66221773e-01  -2.49156252e+00
   9.36589652e-01  -2.28859753e+00
   1.00829591e+00  -2.08807524e+00
   1.08153909e+00  -1.88987380e+00
   1.15649929e+00  -1.69387238e+00
   1.23334222e+00  -1.49995488e+00
   1.31222290e+00  -1.30801063e+00
   1.39328693e+00  -1.11793724e+00
   1.47667226e+00  -9.29639044e-01
   1.56250971e+00  -7.43031053e-01
   1.65092494e+00  -5.58034746e-01
   1.74203887e+00  -3.74583411e-01
   1.83596923e+00  -1.92617612e-01
   1.93283185e+00  -1.20869246e-02
   2.03274086e+00   1.67049391e-01
   2.13581063e+00   3.44825896e-01
   2.20670777e+00   4.62454624e-01
   2.24272169e+00   5.21050184e-01
   4.70263261e-01  -2.95404625e+00
   4.92082418e-01  -2.88356300e+00
   5.35958748e-01  -2.74356546e+00
   6.02706284e-01  -2.53635351e+00
   6.70626398e-01  -2.33179725e+00
   7.39951398e-01  -2.12976229e+00
   8.10884639e-01  -1.93011194e+00
   8.83608122e-01  -1.73271261e+00
   9.58291129e-01  -1.53743622e+00
   1.03509268e+00  -1.34416185e+00
   1.11416240e+00  -1.15277621e+00
   1.19564045e+00  -9.63175231e-01
   1.27965897e+00  -7.75263642e-01
   1.36634305e+00  -5.88956866e-01
   1.45581251e+00  -4.04179222e-01
   1.54818279e+00  -2.20866501e-01
   1.64356648e+00  -3.89633131e-02
   1.74207429e+00   1.41575390e-01
   1.84381583e+00   3.20784981e-01
   1.94890099e+00   4.98692876e-01
   2.05744051e+00   6.75317759e-01
   2.13217815e+00   7.92220372e-01
   2.17016081e+00   8.50460982e-01
   3.40379993e-01  -2.57946973e+00
   3.61917229e-01  -2.51028132e+00
   4.05378185e-01  -2.37283631e+00
   4.71989539e-01  -2.16930714e+00
   5.40246316e-01  -1.96825963e+00
   6.10345720e-01  -1.76954160e+00
   6.82470932e-01  -1.57300870e+00
   7.56793584e-01  -1.37852471e+00
   8.33471662e-01  -1.18596252e+00
   9.12650625e-01  -9.95204672e-01
   9.94464815e-01  -8.06144401e-01
   1.07904012e+00  -6.18685559e-01
   1.16649554e+00  -4.32743555e-01
   1.25694503e+00  -2.48244549e-01
   1.35049855e+00  -6.51266665e-02
   1.44726355e+00   1.16661415e-01
   1.54734585e+00   2.97159520e-01
   1.65085064e+00   4.76396916e-01
   1.75788347e+00   6.54393130e-01
   1.86855090e+00   8.31157956e-01
   1.98296138e+00   1.00669337e+00
   2.06180457e+00   1.12289407e+00
   2.10188759e+00   1.18078703e+00
   2.05128836e-01  -2.20691007e+00
   2.26552275e-01  -2.13900325e+00
   2.69966156e-01  -2.00406147e+00
   3.36998344e-01  -1.80408874e+00
   4.06137265e-01  -1.60638944e+00
   4.77564025e-01  -1.41080803e+00
   5.51443777e-01  -1.21719919e+00
   6.27924982e-01  -1.02542905e+00
   7.07144043e-01  -8.35375397e-01
   7.89227223e-01  -6.46928371e-01
   8.74293439e-01  -4.59990239e-01
   9.62455220e-01  -2.74476003e-01
   1.05382054e+00  -9.03130384e-02
   1.14849381e+00   9.25582452e-02
   1.24657734e+00   2.74185111e-01
   1.34817224e+00   4.54601983e-01
   1.45337938e+00   6.33831249e-01
   1.56230023e+00   8.11883680e-01
   1.67503740e+00   9.88758942e-01
   1.79169536e+00   1.16444713e+00
   1.91238100e+00   1.33892988e+00
   1.99559654e+00   1.45443151e+00
   2.03791297e+00   1.51197248e+00
   6.40219544e-02  -1.83646540e+00
   8.55796371e-02  -1.76980393e+00
   1.29420299e-01  -1.63727830e+00
   1.97553999e-01  -1.44070188e+00
   2.68235485e-01  -1.24617073e+00
   3.41621130e-01  -1.05353056e+00
   4.17851056e-01  -8.62640808e-01
   4.97055022e-01  -6.73374079e-01
   5.79352538e-01  -4.85616804e-01
   6.64855960e-01  -2.99268941e-01
   7.53671062e-01  -1.14244618e-01
   8.45899575e-01   6.95280317e-02
   9.41640103e-01   2.52106359e-01
   1.04098983e+00   4.33533529e-01
   1.14404526e+00   6.13838200e-01
   1.25090321e+00   7.93035092e-01
   1.36166137e+00   9.71125257e-01
   1.47641883e+00   1.14809679e+00
   1.59527646e+00   1.32392608e+00
   1.71833734e+00   1.49857912e+00
   1.84570708e+00   1.67201356e+00
   1.93356548e+00   1.78679205e+00
   1.97824980e+00   1.84396170e+00
  -8.26292156e-02  -1.46821596e+00
  -6.07235397e-02  -1.40274869e+00
  -1.60255399e-02  -1.27252780e+00
   5.38406942e-02  -1.07916149e+00
   1.26672532e-01  -8.87596729e-01
   2.02600169e-01  -6.97686223e-01
   2.81744774e-01  -5.09296608e-01
   3.64216101e-01  -3.22310078e-01
   4.50117928e-01  -1.36623661e-01
   5.39547744e-01   4.78497424e-02
   6.32600430e-01   2.31181593e-01
   7.29368427e-01   4.13427050e-01
   8.29943836e-01   5.94625102e-01
   9.34418717e-01   7.74798206e-01
   1.04288620e+00   9.53952626e-01
   1.15544070e+00   1.13207861e+00
   1.27217833e+00   1.30915109e+00
   1.39319698e+00   1.48513080e+00
   1.51859637e+00   1.65996563e+00
   1.64847807e+00   1.83359283e+00
   1.78294565e+00   2.00594159e+00
   1.87571842e+00   2.11993811e+00
   1.92290481e+00   2.17669805e+00
  -2.34941318e-01  -1.10225166e+00
  -2.12447170e-01  -1.03791488e+00
  -1.66428297e-01  -9.09866462e-01
  -9.41688973e-02  -7.19495811e-01
  -1.85602821e-02  -5.30672714e-01
   6.05086127e-02  -3.43257021e-01
   1.43136069e-01  -1.57126227e-01
   2.29417155e-01   2.78262721e-02
   3.19440550e-01   2.11689265e-01
   4.13294364e-01   3.94534292e-01
   5.11064640e-01   5.76414469e-01
   6.12838593e-01   7.57364589e-01
   7.18704066e-01   9.37400476e-01
   8.28751049e-01   1.11651917e+00
   9.43071333e-01   1.29469894e+00
   1.06175891e+00   1.47189987e+00
   1.18490954e+00   1.64806488e+00
   1.31262055e+00   1.82312115e+00
   1.44499032e+00   1.99698231e+00
   1.58211804e+00   2.16955130e+00
   1.72410351e+00   2.34072396e+00
   1.82206633e+00   2.45383714e+00
   1.87189145e+00   2.51012598e+00
  -3.92795986e-01  -7.38654954e-01
  -3.69486676e-01  -6.75375515e-01
  -3.21697762e-01  -5.49345636e-01
  -2.46408505e-01  -3.61729215e-01
  -1.67413008e-01  -1.75392356e-01
  -8.46273646e-02   9.79238734e-03
   2.03431513e-03   1.93936437e-01
   9.26499477e-02   3.77130795e-01
   1.87300488e-01   5.59447783e-01
   2.86064762e-01   7.40938703e-01
   3.89025351e-01   9.21634238e-01
   4.96266102e-01   1.10154321e+00
   6.07874687e-01   1.28065272e+00
   7.23941170e-01   1.45892779e+00
   8.44558618e-01   1.63631195e+00
   9.69821926e-01   1.81272796e+00
   1.09982736e+00   1.98807936e+00
   1.23467143e+00   2.16225270e+00
   1.37445011e+00   2.33512056e+00
   1.51925795e+00   2.50654558e+00
   1.66918784e+00   2.67638537e+00
   1.77261643e+00   2.78846085e+00
   1.82521449e+00   2.84418855e+00
  -5.56201570e-01  -3.77512508e-01
  -5.31840447e-01  -3.15203729e-01
  -4.81833962e-01  -1.91018594e-01
  -4.02871538e-01  -5.87485128e-03
  -3.19891916e-01   1.78267183e-01
  -2.32817941e-01   3.61525561e-01
  -1.41585167e-01   5.43994044e-01
  -4.61191632e-02   7.25746810e-01
   5.36507549e-02   9.06833708e-01
   1.57803467e-01   1.08728167e+00
   2.66419119e-01   1.26709224e+00
   3.79584357e-01   1.44624201e+00
   4.97388684e-01   1.62468155e+00
   6.19925937e-01   1.80233599e+00
   7.47291854e-01   1.97910545e+00
   8.79583573e-01   2.15486662e+00
   1.01689758e+00   2.32947503e+00
   1.15932840e+00   2.50276831e+00
   1.30696693e+00   2.67457062e+00
   1.45989938e+00   2.84469825e+00
   1.61820650e+00   3.01296615e+00
   1.72737833e+00   3.12378636e+00
   1.78288487e+00   3.17882977e+00
  -7.25095520e-01  -1.89075742e-02
  -6.99461529e-01   4.25272521e-02
  -6.46788116e-01   1.65077386e-01
  -5.63543979e-01   3.48070839e-01
  -4.75992903e-01   5.30361847e-01
  -3.84089053e-01   7.12046775e-01
  -2.87762341e-01   8.93203634e-01
  -1.86952426e-01   1.07388119e+00
  -8.15823801e-02   1.25410344e+00
   2.84241327e-02   1.43386455e+00
   1.43154718e-01   1.61313023e+00
   2.62699663e-01   1.79183541e+00
   3.87155966e-01   1.96988506e+00
   5.16622444e-01   2.14715398e+00
   6.51199780e-01   2.32348851e+00
   7.90987003e-01   2.49870869e+00
   9.36079810e-01   2.67261195e+00
   1.08656776e+00   2.84497794e+00
   1.24253248e+00   3.01557485e+00
   1.40404587e+00   3.18416714e+00
   1.57116987e+00   3.35052459e+00
   1.68636066e+00   3.45979660e+00
   1.74490699e+00   3.51399276e+00
  -8.99454026e-01   3.37074560e-01
  -8.72312510e-01   3.97758160e-01
  -8.16562624e-01   5.18908146e-01
  -7.28423841e-01   7.00143098e-01
  -6.35757166e-01   8.80984131e-01
  -5.38490501e-01   1.06151680e+00
  -4.36578813e-01   1.24178887e+00
  -3.29943077e-01   1.42182297e+00
  -2.18511764e-01   1.60160589e+00
  -1.02192911e-01   1.78109261e+00
   1.91059268e-02   1.96020137e+00
   1.45488379e-01   2.13881532e+00
   2.77059129e-01   2.31678111e+00
   4.13926101e-01   2.49391092e+00
   5.56194305e-01   2.66998431e+00
   7.03964258e-01   2.84475239e+00
   8.57327527e-01   3.01794310e+00
   1.01636417e+00   3.18926862e+00
   1.18113972e+00   3.35843410e+00
   1.35170394e+00   3.52514857e+00
   1.52808968e+00   3.68913614e+00
   1.64957386e+00   3.79647921e+00
   1.71129111e+00   3.84962129e+00
  -1.07922025e+00   6.90355259e-01
  -1.05038292e+00   7.50417861e-01
  -9.91117145e-01   8.70472567e-01
  -8.97551985e-01   1.05040230e+00
  -7.99224725e-01   1.23028395e+00
  -6.96118119e-01   1.41016207e+00
  -5.88141555e-01   1.59006136e+00
  -4.75232186e-01   1.76996110e+00
  -3.57287554e-01   1.94980659e+00
  -2.34212440e-01   2.12949845e+00
  -1.05891331e-01   2.30889679e+00
   2.77894853e-02   2.48781717e+00
   1.66950330e-01   2.66603362e+00
   3.11706613e-01   2.84327951e+00
   4.62168740e-01   3.01925254e+00
   6.18434852e-01   3.19362044e+00
   7.80587877e-01   3.36602961e+00
   9.48690647e-01   3.53611543e+00
   1.12278376e+00   3.70351496e+00
   1.30288300e+00   3.86788086e+00
   1.48898171e+00   4.02889746e+00
   1.61702718e+00   4.13383015e+00
   1.68203606e+00   4.18565802e+00
  -1.26437749e+00   1.04084207e+00
  -1.23360176e+00   1.10047420e+00
  -1.17050521e+00   1.21976381e+00
  -1.07094134e+00   1.39896657e+00
  -9.66509933e-01   1.57846673e+00
  -8.57084422e-01   1.75829928e+00
  -7.42622801e-01   1.93843491e+00
  -6.22999673e-01   2.11881204e+00
  -4.98119075e-01   2.29931276e+00
  -3.67844984e-01   2.47977385e+00
  -2.32051778e-01   2.65997687e+00
  -9.05992930e-02   2.83965365e+00
   5.66436596e-02   3.01848497e+00
   2.09804404e-01   3.19610699e+00
   3.68993781e-01   3.37211694e+00
   5.34303851e-01   3.54608362e+00
   7.05800107e-01   3.71755934e+00
   8.83518484e-01   3.88609529e+00
   1.06746093e+00   4.05125799e+00
   1.25759682e+00   4.21264915e+00
   1.45386145e+00   4.36992259e+00
   1.58873145e+00   4.47184558e+00
   1.65715951e+00   4.52204728e+00
  -1.45483762e+00   1.38847314e+00
  -1.42202977e+00   1.44784838e+00
  -1.35465280e+00   1.56684744e+00
  -1.24872786e+00   1.74598229e+00
  -1.13770273e+00   1.92582874e+00
  -1.02159328e+00   2.10634177e+00
  -9.00222676e-01   2.28745969e+00
  -7.73504282e-01   2.46904489e+00
  -6.41265941e-01   2.65091257e+00
  -5.03369533e-01   2.83280728e+00
  -3.59643626e-01   3.01441519e+00
  -2.09935404e-01   3.19535732e+00
  -5.40906770e-02   3.37519903e+00
   1.08021985e-01   3.55345474e+00
   2.76512659e-01   3.72960111e+00
   4.51457034e-01   3.90309074e+00
   6.32893241e-01   4.07337095e+00
   8.20814503e-01   4.23990381e+00
   1.01516982e+00   4.40218978e+00
   1.21586074e+00   4.55979014e+00
   1.42275246e+00   4.71235284e+00
   1.56470221e+00   4.81054177e+00
   1.63664131e+00   4.85873022e+00
  -1.65063863e+00   1.73312968e+00
  -1.61549118e+00   1.79257225e+00
  -1.54375917e+00   1.91174230e+00
  -1.43091958e+00   2.09169443e+00
  -1.31304841e+00   2.27274304e+00
  -1.18984110e+00   2.45484571e+00
  -1.06125499e+00   2.63784207e+00
  -9.27049777e-01   2.82153157e+00
  -7.87082000e-01   3.00561852e+00
  -6.41129604e-01   3.18974167e+00
  -4.89013683e-01   3.37345422e+00
  -3.30538500e-01   3.55624064e+00
  -1.65542495e-01   3.73751764e+00
   6.11511809e-03   3.91665205e+00
   1.84530612e-01   4.09297580e+00
   3.69754558e-01   4.26580954e+00
   5.61779436e-01   4.43448646e+00
   7.60539691e-01   4.59838171e+00
   9.65905770e-01   4.75693938e+00
   1.17769506e+00   4.90970551e+00
   1.39567317e+00   5.05635123e+00
   1.54493569e+00   5.14991273e+00
   1.62053172e+00   5.19565376e+00
  -1.85158023e+00   2.07480269e+00
  -1.81427122e+00   2.13451035e+00
  -1.73759193e+00   2.25463078e+00
  -1.61784578e+00   2.43637109e+00
  -1.49267826e+00   2.61973201e+00
  -1.36220646e+00   2.80451349e+00
  -1.22604535e+00   2.99051398e+00
  -1.08407578e+00   3.17739336e+00
  -9.35988438e-01   3.36474549e+00
  -7.81580761e-01   3.55204655e+00
  -6.20592027e-01   3.73868980e+00
  -4.52820616e-01   3.92397607e+00
  -2.78076404e-01   4.10714094e+00
  -9.62286846e-02   4.28736932e+00
   9.28008912e-02   4.46382611e+00
   2.89016194e-01   4.63568426e+00
   4.92347067e-01   4.80216090e+00
   7.02638800e-01   4.96255100e+00
   9.19663091e-01   5.11626736e+00
   1.14311842e+00   5.26287389e+00
   1.37265041e+00   5.40211678e+00
   1.52949072e+00   5.49002737e+00
   1.60874498e+00   5.53275384e+00
  -2.05790912e+00   2.41327605e+00
  -2.01782050e+00   2.47386168e+00
  -1.93675117e+00   2.59553694e+00
  -1.80941307e+00   2.78045669e+00
  -1.67707393e+00   2.96743001e+00
  -1.53897983e+00   3.15629903e+00
  -1.39513553e+00   3.34667235e+00
  -1.24506632e+00   3.53811095e+00
  -1.08857028e+00   3.73000200e+00
  -9.25279823e-01   3.92163887e+00
  -7.54947567e-01   4.11218366e+00
  -5.77305358e-01   4.30071512e+00
  -3.92170824e-01   4.48623768e+00
  -1.99414619e-01   4.66772425e+00
   9.96568116e-04   4.84414729e+00
   2.09004669e-01   5.01452399e+00
   4.24441192e-01   5.17795649e+00
   6.47037893e-01   5.33368171e+00
   8.76424063e-01   5.48111375e+00
   1.11214721e+00   5.61988811e+00
   1.35372276e+00   5.74991076e+00
   1.51826205e+00   5.83083094e+00
   1.60144814e+00   5.86998680e+00
  -2.26902165e+00   2.74872974e+00
  -2.22715556e+00   2.81027935e+00
  -2.14043808e+00   2.93486255e+00
  -2.00637408e+00   3.12441326e+00
  -1.86634821e+00   3.31675562e+00
  -1.72084131e+00   3.51141416e+00
  -1.56901764e+00   3.70794738e+00
  -1.41076117e+00   3.90563526e+00
  -1.24551327e+00   4.10366884e+00
  -1.07299339e+00   4.30104044e+00
  -8.92807222e-01   4.49664165e+00
  -7.04702349e-01   4.68925315e+00
  -5.08462308e-01   4.87761131e+00
  -3.03998265e-01   5.06043786e+00
  -9.13286743e-02   5.23649715e+00
   1.29384423e-01   5.40464184e+00
   3.57846219e-01   5.56387296e+00
   5.93620867e-01   5.71339506e+00
   8.36150828e-01   5.85267335e+00
   1.08481676e+00   5.98150748e+00
   1.33886567e+00   6.10000486e+00
   1.51154457e+00   6.17257618e+00
   1.59833635e+00   6.20727094e+00
  -2.48591132e+00   3.08059895e+00
  -2.44042843e+00   3.14443225e+00
  -2.35039777e+00   3.27259868e+00
  -2.20824363e+00   3.46904697e+00
  -2.06143851e+00   3.66883657e+00
  -1.90815473e+00   3.87161174e+00
  -1.74863395e+00   4.07652050e+00
  -1.58194070e+00   4.28266523e+00
  -1.40783111e+00   4.48881929e+00
  -1.22569351e+00   4.69365051e+00
  -1.03519492e+00   4.89565644e+00
  -8.35973002e-01   5.09328332e+00
  -6.27848211e-01   5.28494132e+00
  -4.10754760e-01   5.46908048e+00
  -1.84814376e-01   5.64423461e+00
   4.96796491e-02   5.80909205e+00
   2.92241936e-01   5.96256263e+00
   5.42209815e-01   6.10385380e+00
   7.98810751e-01   6.23257286e+00
   1.06107638e+00   6.34872668e+00
   1.32828428e+00   6.45296779e+00
   1.50872447e+00   6.51496025e+00
   1.59997824e+00   6.54459533e+00
  -2.70657756e+00   3.40971607e+00
  -2.66111100e+00   3.47528823e+00
  -2.56402863e+00   3.60957802e+00
  -2.41673651e+00   3.81525959e+00
  -2.26224777e+00   4.02549995e+00
  -2.10217259e+00   4.23926188e+00
  -1.93472930e+00   4.45559602e+00
  -1.75993536e+00   4.67296176e+00
  -1.57676684e+00   4.88975721e+00
  -1.38483490e+00   5.10410525e+00
  -1.18352768e+00   5.31409846e+00
  -9.72532535e-01   5.51776494e+00
  -7.51627460e-01   5.71317767e+00
  -5.20840407e-01   5.89847707e+00
  -2.80410384e-01   6.07194915e+00
  -3.08349921e-02   6.23209693e+00
   2.27134006e-01   6.37773565e+00
   4.92560974e-01   6.50813481e+00
   7.64218646e-01   6.62305356e+00
   1.04110960e+00   6.72306622e+00
   1.32156109e+00   6.80908549e+00
   1.51117833e+00   6.85892875e+00
   1.60531536e+00   6.88181703e+00
  -2.93461638e+00   3.73430253e+00
  -2.88288177e+00   3.80489814e+00
  -2.78632466e+00   3.94586584e+00
  -2.63022403e+00   4.16476896e+00
  -2.47063019e+00   4.38920538e+00
  -2.30327143e+00   4.61824421e+00
  -2.12910223e+00   4.84985429e+00
  -1.94624552e+00   5.08209825e+00
  -1.75439091e+00   5.31255448e+00
  -1.55246951e+00   5.53888534e+00
  -1.33999758e+00   5.75865960e+00
  -1.11648309e+00   5.96953003e+00
  -8.81786357e-01   6.16918403e+00
  -6.36003281e-01   6.35542405e+00
  -3.79570754e-01   6.52622134e+00
  -1.13274195e-01   6.67982533e+00
   1.61807323e-01   6.81494388e+00
   4.44161817e-01   6.93083972e+00
   7.32435257e-01   7.02776726e+00
   1.02444628e+00   7.10658579e+00
   1.31982179e+00   7.17009785e+00
   1.51606834e+00   7.20311093e+00
   1.61632399e+00   7.21903978e+00
  -3.16312568e+00   4.05747842e+00
  -3.11750963e+00   4.13022436e+00
  -3.00934958e+00   4.28316906e+00
  -2.85244907e+00   4.52011201e+00
  -2.68580517e+00   4.76485672e+00
  -2.51403802e+00   5.01460384e+00
  -2.33335508e+00   5.26687413e+00
  -2.14390150e+00   5.51830034e+00
  -1.94366642e+00   5.76602614e+00
  -1.73200256e+00   6.00709493e+00
  -1.50797525e+00   6.23876859e+00
  -1.27119815e+00   6.45828397e+00
  -1.02148858e+00   6.66293528e+00
  -7.59093554e-01   6.85006095e+00
  -4.84700099e-01   7.01715265e+00
  -1.99439114e-01   7.16205422e+00
   9.49152578e-02   7.28312693e+00
   3.96552497e-01   7.37979959e+00
   7.02595117e-01   7.45235774e+00
   1.01204832e+00   7.50353449e+00
   1.32061473e+00   7.53591465e+00
   1.52927474e+00   7.55115506e+00
   1.62928861e+00   7.55590474e+00
  -3.40511310e+00   4.37307348e+00
  -3.34312664e+00   4.45745499e+00
  -3.24680874e+00   4.62323610e+00
  -3.07871927e+00   4.88720729e+00
  -2.91164992e+00   5.16076295e+00
  -2.73580423e+00   5.43961527e+00
  -2.55243033e+00   5.71846935e+00
  -2.35736684e+00   5.99398197e+00
  -2.15003618e+00   6.26271300e+00
  -1.92883169e+00   6.52175918e+00
  -1.69310193e+00   6.76805394e+00
  -1.44221484e+00   6.99850087e+00
  -1.17603876e+00   7.20981110e+00
  -8.94912436e-01   7.39859070e+00
  -5.99777103e-01   7.56149996e+00
  -2.92485022e-01   7.69547052e+00
   2.47038080e-02   7.79834318e+00
   3.48048991e-01   7.86893668e+00
   6.75443360e-01   7.90883454e+00
   1.00130746e+00   7.92045075e+00
   1.32888739e+00   7.91329001e+00
   1.53870480e+00   7.89730123e+00
   1.65131427e+00   7.89293253e+00
  -3.63395666e+00   4.69340998e+00
  -3.60215675e+00   4.77797097e+00
  -3.47266588e+00   4.97203521e+00
  -3.31544094e+00   5.28065637e+00
  -3.14933431e+00   5.59674542e+00
  -2.97830961e+00   5.91168527e+00
  -2.79345670e+00   6.22278661e+00
  -2.59556266e+00   6.52654897e+00
  -2.38208128e+00   6.82057187e+00
  -2.15231340e+00   7.10186587e+00
  -1.90500914e+00   7.36732041e+00
  -1.63944292e+00   7.61325875e+00
  -1.35519946e+00   7.83550051e+00
  -1.05250704e+00   8.02936037e+00
  -7.32715179e-01   8.18981635e+00
  -3.98100740e-01   8.31213400e+00
  -5.31871924e-02   8.39224490e+00
   2.98122983e-01   8.42864728e+00
   6.47649143e-01   8.42121295e+00
   9.96234255e-01   8.37722180e+00
   1.33154576e+00   8.30212719e+00
   1.56922177e+00   8.25711175e+00
   1.66772918e+00   8.22887469e+00
  -3.82376295e+00   4.88859613e+00
  -3.72358688e+00   5.00649682e+00
  -3.63387004e+00   5.23673413e+00
  -3.48462792e+00   5.58719815e+00
  -3.33098676e+00   5.93322942e+00
  -3.16144079e+00   6.27497162e+00
  -2.97870499e+00   6.60953925e+00
  -2.77986339e+00   6.93550627e+00
  -2.56423642e+00   7.25044164e+00
  -2.33016780e+00   7.55177458e+00
  -2.07632316e+00   7.83616393e+00
  -1.80134986e+00   8.09949213e+00
  -1.50423967e+00   8.33661459e+00
  -1.18479948e+00   8.54126748e+00
  -8.44012124e-01   8.70628671e+00
  -4.85328352e-01   8.82413354e+00
  -1.13837970e-01   8.88855773e+00
   2.61328659e-01   8.89558696e+00
   6.34213601e-01   8.84669877e+00
   9.91577927e-01   8.74465930e+00
   1.34113787e+00   8.60337920e+00
   1.55237418e+00   8.48568238e+00
   1.70176458e+00   8.45425287e+00
  -3.84693505e+00   5.01939866e+00
  -3.80638269e+00   5.14362672e+00
  -3.72147227e+00   5.39084440e+00
  -3.58177335e+00   5.75721130e+00
  -3.42900095e+00   6.11833256e+00
  -3.26222232e+00   6.47321767e+00
  -3.08039607e+00   6.82065243e+00
  -2.88229953e+00   7.15910189e+00
  -2.66654533e+00   7.48661526e+00
  -2.43156912e+00   7.80067925e+00
  -2.17565975e+00   8.09801647e+00
  -1.89706709e+00   8.37434247e+00
  -1.59421045e+00   8.62403892e+00
  -1.26616962e+00   8.83990933e+00
  -9.13463283e-01   9.01309363e+00
  -5.39224294e-01   9.13371200e+00
  -1.50248884e-01   9.19267802e+00
   2.43163010e-01   9.18466237e+00
   6.29471470e-01   9.11042538e+00
   9.99078512e-01   8.97646880e+00
   1.34611453e+00   8.79231362e+00
   1.56080764e+00   8.64254467e+00
   1.66400376e+00   8.56238086e+00
    </coefs> 
   </Geometry> 
</xml>