<?xml version="1.0" encoding="UTF-8"?>
 <xml> 
   <Geometry type="TensorBSpline2" id="0"> 
   <Basis type="TensorBSplineBasis2"> 
     <Basis type="BSplineBasis" index="0"> 
<KnotVector degree="3">  0.    0.    0.    0.    0.05  0.1   0.15  0.2   0.25  0.3   0.35  0.4
  0.45  0.5   0.55  0.6   0.65  0.7   0.75  0.8   0.85  0.9   0.95  1.    1.
  1.    1.   </KnotVector> 
     </Basis> 
     <Basis type="BSplineBasis" index="1"> 
<KnotVector degree="3">  0.     0.     0.     0.     0.025  0.05   0.075  0.1    0.125  0.15
  0.175  0.2    0.225  0.25   0.275  0.3    0.325  0.35   0.375  0.4    0.425
  0.45   0.475  0.5    0.525  0.55   0.575  0.6    0.625  0.65   0.675  0.7
  0.725  0.75   0.775  0.8    0.825  0.85   0.875  0.9    0.925  0.95
  0.975  1.     1.     1.     1.    </KnotVector> 
     </Basis> 
    </Basis> 
    <coefs geoDim="2"> 
 -3.03753865e+00  -6.89082258e+00
  -2.95966679e+00  -7.02805868e+00
  -2.79596172e+00  -7.29804253e+00
  -2.52371173e+00  -7.68567025e+00
  -2.22191690e+00  -8.05091749e+00
  -1.88745548e+00  -8.38676251e+00
  -1.51751830e+00  -8.68351756e+00
  -1.11069533e+00  -8.92806339e+00
  -6.69229607e-01  -9.10393778e+00
  -2.02055486e-01  -9.19387625e+00
   2.73850255e-01  -9.18634697e+00
   7.38039591e-01  -9.08242464e+00
   1.17463599e+00  -8.89501031e+00
   1.57589657e+00  -8.64157545e+00
   1.94031639e+00  -8.33814666e+00
   2.26963408e+00  -7.99730263e+00
   2.56676002e+00  -7.62827315e+00
   2.83478574e+00  -7.23773001e+00
   3.07656700e+00  -6.83050055e+00
   3.29457979e+00  -6.41012441e+00
   3.49097306e+00  -5.97926064e+00
   3.60862429e+00  -5.68634688e+00
   3.66443061e+00  -5.53875375e+00
  -2.97941715e+00  -6.80865859e+00
  -2.92204905e+00  -6.86375168e+00
  -2.75350756e+00  -7.08301255e+00
  -2.47932172e+00  -7.40376924e+00
  -2.17598564e+00  -7.71311034e+00
  -1.84551239e+00  -7.99246068e+00
  -1.48542944e+00  -8.23594024e+00
  -1.09724493e+00  -8.43144658e+00
  -6.84491479e-01  -8.56870266e+00
  -2.54750352e-01  -8.63770009e+00
   1.81243983e-01  -8.63254248e+00
   6.11211906e-01  -8.55266248e+00
   1.02400701e+00  -8.40342153e+00
   1.41179800e+00  -8.19425268e+00
   1.77067051e+00  -7.93606270e+00
   2.09979262e+00  -7.63894732e+00
   2.40011612e+00  -7.31162671e+00
   2.67362431e+00  -6.96071643e+00
   2.92229071e+00  -6.59253734e+00
   3.14891912e+00  -6.21057706e+00
   3.35445859e+00  -5.82368538e+00
   3.47938073e+00  -5.56790294e+00
   3.53037870e+00  -5.46824663e+00
  -2.91114534e+00  -6.62822534e+00
  -2.83717625e+00  -6.68317560e+00
  -2.68796779e+00  -6.78617517e+00
  -2.41637606e+00  -7.00489434e+00
  -2.12264855e+00  -7.21882498e+00
  -1.80448670e+00  -7.41976195e+00
  -1.46556661e+00  -7.59143135e+00
  -1.10678153e+00  -7.72746753e+00
  -7.32088652e-01  -7.81922541e+00
  -3.46544353e-01  -7.86119408e+00
   4.29617539e-02  -7.84946447e+00
   4.29003799e-01  -7.78354499e+00
   8.04660371e-01  -7.66582157e+00
   1.16445278e+00  -7.50106686e+00
   1.50468448e+00  -7.29530352e+00
   1.82336082e+00  -7.05518781e+00
   2.11999666e+00  -6.78702340e+00
   2.39494935e+00  -6.49736723e+00
   2.64970062e+00  -6.19151900e+00
   2.88521766e+00  -5.87782249e+00
   3.10444194e+00  -5.56302012e+00
   3.23867238e+00  -5.36899640e+00
   3.30887089e+00  -5.26785117e+00
  -2.88739203e+00  -6.33185906e+00
  -2.79779965e+00  -6.36417022e+00
  -2.62409785e+00  -6.44506821e+00
  -2.35940368e+00  -6.56639433e+00
  -2.07659871e+00  -6.69452144e+00
  -1.77875185e+00  -6.81179341e+00
  -1.46580193e+00  -6.91225460e+00
  -1.14050484e+00  -6.98733056e+00
  -8.05325330e-01  -7.03246099e+00
  -4.63958987e-01  -7.04344532e+00
  -1.20413281e-01  -7.01817695e+00
   2.20996387e-01  -6.95588558e+00
   5.56150543e-01  -6.85750171e+00
   8.81471875e-01  -6.72530928e+00
   1.19423078e+00  -6.56273525e+00
   1.49267239e+00  -6.37381526e+00
   1.77590617e+00  -6.16313462e+00
   2.04398107e+00  -5.93517648e+00
   2.29740603e+00  -5.69525476e+00
   2.53792529e+00  -5.44765850e+00
   2.76725747e+00  -5.19885780e+00
   2.91695105e+00  -5.03117026e+00
   2.99028708e+00  -4.95114653e+00
  -2.84142658e+00  -6.04357900e+00
  -2.75903103e+00  -6.06650950e+00
  -2.58909888e+00  -6.11013587e+00
  -2.32513209e+00  -6.18582380e+00
  -2.05340739e+00  -6.25703543e+00
  -1.77158486e+00  -6.32148005e+00
  -1.48084321e+00  -6.37190016e+00
  -1.18211878e+00  -6.40469763e+00
  -8.77543054e-01  -6.41576623e+00
  -5.69404942e-01  -6.40275877e+00
  -2.60420782e-01  -6.36402468e+00
   4.66756797e-02  -6.29916300e+00
   3.49279780e-01  -6.20869717e+00
   6.45136748e-01  -6.09406289e+00
   9.32462072e-01  -5.95736133e+00
   1.21001232e+00  -5.80127493e+00
   1.47716385e+00  -5.62875380e+00
   1.73381128e+00  -5.44313455e+00
   1.98056470e+00  -5.24747891e+00
   2.21831981e+00  -5.04544942e+00
   2.44900175e+00  -4.83939799e+00
   2.59854127e+00  -4.70315789e+00
   2.67333555e+00  -4.63379988e+00
  -2.81078013e+00  -5.75086205e+00
  -2.72624225e+00  -5.76334123e+00
  -2.55854425e+00  -5.79122139e+00
  -2.30356064e+00  -5.82877524e+00
  -2.04260418e+00  -5.86354446e+00
  -1.77615984e+00  -5.88998808e+00
  -1.50425564e+00  -5.90582161e+00
  -1.22800808e+00  -5.90764808e+00
  -9.48622916e-01  -5.89353643e+00
  -6.67735778e-01  -5.86177708e+00
  -3.87040986e-01  -5.81156024e+00
  -1.08282454e-01  -5.74262984e+00
   1.66910757e-01  -5.65540663e+00
   4.37114643e-01  -5.55084672e+00
   7.01207599e-01  -5.43039614e+00
   9.58435394e-01  -5.29582585e+00
   1.20841608e+00  -5.14919636e+00
   1.45120245e+00  -4.99260105e+00
   1.68715995e+00  -4.82834763e+00
   1.91716839e+00  -4.65832860e+00
   2.14219815e+00  -4.48484397e+00
   2.29034316e+00  -4.36692394e+00
   2.36388737e+00  -4.30858032e+00
  -2.77718998e+00  -5.45985996e+00
  -2.69714656e+00  -5.46530747e+00
  -2.53510472e+00  -5.47469276e+00
  -2.28899702e+00  -5.48745383e+00
  -2.04015402e+00  -5.49428255e+00
  -1.78817727e+00  -5.49409603e+00
  -1.53359234e+00  -5.48437618e+00
  -1.27696290e+00  -5.46375121e+00
  -1.01924662e+00  -5.43076490e+00
  -7.61467419e-01  -5.38463136e+00
  -5.04757827e-01  -5.32488562e+00
  -2.50213463e-01  -5.25155893e+00
   1.15861788e-03  -5.16505353e+00
   2.48514110e-01  -5.06613280e+00
   4.91215110e-01  -4.95583004e+00
   7.28860713e-01  -4.83540761e+00
   9.61320255e-01  -4.70624148e+00
   1.18871171e+00  -4.56982557e+00
   1.41145739e+00  -4.42755522e+00
   1.63016044e+00  -4.28093672e+00
   1.84578784e+00  -4.13106848e+00
   1.98797611e+00  -4.03028982e+00
   2.05907058e+00  -3.97934551e+00
  -2.75021640e+00  -5.16741109e+00
  -2.67180017e+00  -5.16634986e+00
  -2.51544922e+00  -5.16390360e+00
  -2.28006846e+00  -5.15527141e+00
  -2.04334080e+00  -5.14152603e+00
  -1.80555953e+00  -5.12078405e+00
  -1.56696291e+00  -5.09214050e+00
  -1.32810601e+00  -5.05448502e+00
  -1.08958990e+00  -5.00721565e+00
  -8.52128250e-01  -4.94989450e+00
  -6.16426609e-01  -4.88243695e+00
  -3.83162772e-01  -4.80500111e+00
  -1.52928621e-01  -4.71800914e+00
   7.38026270e-02  -4.62208950e+00
   2.96708698e-01  -4.51804875e+00
   5.15640512e-01  -4.40680902e+00
   7.30626578e-01  -4.28938253e+00
   9.41892184e-01  -4.16678616e+00
   1.14982757e+00  -4.04007610e+00
   1.35504151e+00  -3.91017346e+00
   1.55825476e+00  -3.77806994e+00
   1.69315025e+00  -3.68878163e+00
   1.76054683e+00  -3.64420322e+00
  -2.72477601e+00  -4.87525598e+00
  -2.65000046e+00  -4.86905876e+00
  -2.50019432e+00  -4.85520212e+00
  -2.27554651e+00  -4.83041160e+00
  -2.05113773e+00  -4.80006926e+00
  -1.82702337e+00  -4.76363043e+00
  -1.60352453e+00  -4.72028848e+00
  -1.38099139e+00  -4.66962227e+00
  -1.15987467e+00  -4.61128594e+00
  -9.40627551e-01  -4.54519255e+00
  -7.23701691e-01  -4.47141753e+00
  -5.09498487e-01  -4.39023099e+00
  -2.98346917e-01  -4.30205282e+00
  -9.04781835e-02  -4.20743617e+00
   1.13989859e-01  -4.10703022e+00
   3.15063084e-01  -4.00155735e+00
   5.12881704e-01  -3.89177177e+00
   7.07716025e-01  -3.77845234e+00
   8.99983214e-01  -3.66233925e+00
   1.09021941e+00  -3.54418336e+00
   1.27913134e+00  -3.42461247e+00
   1.40467870e+00  -3.34450801e+00
   1.46756486e+00  -3.30431509e+00
  -2.70358839e+00  -4.58252168e+00
  -2.63169782e+00  -4.57180599e+00
  -2.48852116e+00  -4.54925302e+00
  -2.27502645e+00  -4.51072920e+00
  -2.06275328e+00  -4.46725723e+00
  -1.85189864e+00  -4.41823818e+00
  -1.64266566e+00  -4.36338811e+00
  -1.43534198e+00  -4.30245829e+00
  -1.23021964e+00  -4.23539483e+00
  -1.02759914e+00  -4.16225352e+00
  -8.27750245e-01  -4.08323315e+00
  -6.30898810e-01  -3.99864020e+00
  -4.37206897e-01  -3.90888193e+00
  -2.46760541e-01  -3.81444204e+00
  -5.95592897e-02  -3.71586378e+00
   1.24491268e-01  -3.61372581e+00
   3.05581811e-01  -3.50862949e+00
   4.84006317e-01  -3.40117166e+00
   6.60156326e-01  -3.29195111e+00
   8.34539824e-01  -3.18152181e+00
   1.00776078e+00  -3.07044528e+00
   1.12299315e+00  -2.99622269e+00
   1.18066779e+00  -2.95921593e+00
  -2.68520512e+00  -4.28973253e+00
  -2.61677320e+00  -4.27526078e+00
  -2.48050069e+00  -4.24494573e+00
  -2.27808702e+00  -4.19530938e+00
  -2.07779350e+00  -4.14102061e+00
  -1.87972766e+00  -4.08189969e+00
  -1.68407270e+00  -4.01777597e+00
  -1.49101789e+00  -3.94862712e+00
  -1.30076560e+00  -3.87450723e+00
  -1.11350000e+00  -3.79557782e+00
  -9.29378976e-01  -3.71207999e+00
  -7.48517865e-01  -3.62433176e+00
  -5.70980368e-01  -3.53271014e+00
  -3.96770264e-01  -3.43763899e+00
  -2.25826072e-01  -3.33957351e+00
  -5.80176533e-02  -3.23898936e+00
   1.06857604e-01  -3.13636822e+00
   2.69075003e-01  -3.03219404e+00
   4.28989523e-01  -2.92693524e+00
   5.87032422e-01  -2.82105843e+00
   7.43730213e-01  -2.71499488e+00
   8.47693844e-01  -2.64448519e+00
   8.99684515e-01  -2.60931232e+00
  -2.67040380e+00  -3.99666544e+00
  -2.60524817e+00  -3.97893345e+00
  -2.47587152e+00  -3.94226259e+00
  -2.28452884e+00  -3.88321192e+00
  -2.09594501e+00  -3.82002421e+00
  -1.91023655e+00  -3.75258058e+00
  -1.72752490e+00  -3.68088044e+00
  -1.54794733e+00  -3.60497982e+00
  -1.37163121e+00  -3.52501692e+00
  -1.19868907e+00  -3.44118955e+00
  -1.02920561e+00  -3.35375386e+00
  -8.63231434e-01  -3.26301083e+00
  -7.00776700e-01  -3.16929773e+00
  -5.41807168e-01  -3.07297732e+00
  -3.86241355e-01  -2.97442927e+00
  -2.33948457e-01  -2.87404085e+00
  -8.47477309e-02  -2.77220180e+00
   6.15940602e-02  -2.66929591e+00
   2.05362180e-01  -2.56570330e+00
   3.46901763e-01  -2.46178840e+00
   4.86615952e-01  -2.35791662e+00
   5.78870662e-01  -2.28891055e+00
   6.24862618e-01  -2.25454516e+00
  -2.65877422e+00  -3.70349719e+00
  -2.59703248e+00  -3.68299585e+00
  -2.47459917e+00  -3.64079075e+00
  -2.29416413e+00  -3.57385343e+00
  -2.11701723e+00  -3.50319011e+00
  -1.94323165e+00  -3.42881517e+00
  -1.77289904e+00  -3.35078457e+00
  -1.60610771e+00  -3.26921785e+00
  -1.44293927e+00  -3.18427969e+00
  -1.28345838e+00  -3.09617933e+00
  -1.12770831e+00  -3.00516006e+00
  -9.75706005e-01  -2.91149278e+00
  -8.27439321e-01  -2.81546772e+00
  -6.82865233e-01  -2.71738754e+00
  -5.41908991e-01  -2.61756053e+00
  -4.04464089e-01  -2.51629573e+00
  -2.70391979e-01  -2.41389764e+00
  -1.39522839e-01  -2.31066482e+00
  -1.16542151e-02  -2.20688478e+00
   1.13447275e-01  -2.10283903e+00
   2.36050822e-01  -1.99879445e+00
   3.16318775e-01  -1.92961936e+00
   3.56146695e-01  -1.89511175e+00
  -2.65053618e+00  -3.41019080e+00
  -2.59214551e+00  -3.38728644e+00
  -2.47657913e+00  -3.34039248e+00
  -2.30687969e+00  -3.26670852e+00
  -2.14086354e+00  -3.18970857e+00
  -1.97858929e+00  -3.10944511e+00
  -1.82011669e+00  -3.02602065e+00
  -1.66550504e+00  -2.93957274e+00
  -1.51480477e+00  -2.85027297e+00
  -1.36805413e+00  -2.75831860e+00
  -1.22527551e+00  -2.66392726e+00
  -1.08647355e+00  -2.56733022e+00
  -9.51634249e-01  -2.46876681e+00
  -8.20724821e-01  -2.36847896e+00
  -6.93694452e-01  -2.26670678e+00
  -5.70475450e-01  -2.16368440e+00
  -4.50985181e-01  -2.05963749e+00
  -3.35127540e-01  -1.95477986e+00
  -2.22795312e-01  -1.84931358e+00
  -1.13869822e-01  -1.74342454e+00
  -8.22350407e-03  -1.63728720e+00
   6.01165343e-02  -1.56646206e+00
   9.37863765e-02  -1.53106245e+00
  -2.64557385e+00  -3.11682362e+00
  -2.59053420e+00  -3.09184436e+00
  -2.48176852e+00  -3.04086599e+00
  -2.32258014e+00  -2.96137848e+00
  -2.16738658e+00  -2.87891380e+00
  -2.01622546e+00  -2.79355915e+00
  -1.86913876e+00  -2.70542865e+00
  -1.72616574e+00  -2.61466256e+00
  -1.58734043e+00  -2.52142019e+00
  -1.45268878e+00  -2.42587542e+00
  -1.32222752e+00  -2.32821111e+00
  -1.19596376e+00  -2.22861435e+00
  -1.07389548e+00  -2.12727183e+00
  -9.56012793e-01  -2.02436577e+00
  -8.42299711e-01  -1.92007010e+00
  -7.32736408e-01  -1.81454740e+00
  -6.27301557e-01  -1.70794566e+00
  -5.25975601e-01  -1.60039634e+00
  -4.28744502e-01  -1.49201142e+00
  -3.35606574e-01  -1.38288370e+00
  -2.46578538e-01  -1.27308223e+00
  -1.89997569e-01  -1.19946590e+00
  -1.62411121e-01  -1.16255369e+00
  -2.64394942e+00  -2.82341180e+00
  -2.59220545e+00  -2.79661324e+00
  -2.49011903e+00  -2.74208332e+00
  -2.34120226e+00  -2.65752174e+00
  -2.19651625e+00  -2.57026762e+00
  -2.05608887e+00  -2.48041479e+00
  -1.91994977e+00  -2.38807683e+00
  -1.78812871e+00  -2.29338138e+00
  -1.66065314e+00  -2.19646600e+00
  -1.53754746e+00  -2.09747347e+00
  -1.41883288e+00  -1.99654755e+00
  -1.30452805e+00  -1.89382879e+00
  -1.19465041e+00  -1.78945078e+00
  -1.08921811e+00  -1.68353661e+00
  -9.88252671e-01  -1.57619572e+00
  -8.91782535e-01  -1.46752101e+00
  -7.99847808e-01  -1.35758652e+00
  -7.12505419e-01  -1.24644444e+00
  -6.29833817e-01  -1.13412234e+00
  -5.51935546e-01  -1.02061739e+00
  -4.78939671e-01  -9.05893534e-01
  -4.33651144e-01  -8.28545807e-01
  -4.11886469e-01  -7.89638389e-01
  -2.64563197e+00  -2.53000428e+00
  -2.59713366e+00  -2.50160068e+00
  -2.50160066e+00  -2.44392289e+00
  -2.36269725e+00  -2.35485916e+00
  -2.22820666e+00  -2.26332310e+00
  -2.09814996e+00  -2.16940563e+00
  -1.97255235e+00  -2.07320770e+00
  -1.85144097e+00  -1.97483658e+00
  -1.73484448e+00  -1.87440177e+00
  -1.62279307e+00  -1.77201115e+00
  -1.51531934e+00  -1.66776722e+00
  -1.41245994e+00  -1.56176386e+00
  -1.31425780e+00  -1.45408296e+00
  -1.22076514e+00  -1.34479141e+00
  -1.13204669e+00  -1.23393807e+00
  -1.04818271e+00  -1.12155034e+00
  -9.69271323e-01  -1.00763014e+00
  -8.95431297e-01  -8.92150006e-01
  -8.26808054e-01  -7.75049719e-01
  -7.63586776e-01  -6.56234878e-01
  -7.06010282e-01  -5.35574164e-01
  -6.71600930e-01  -4.53787353e-01
  -6.55453055e-01  -4.12517483e-01
  -2.65063937e+00  -2.23663246e+00
  -2.60531872e+00  -2.20678957e+00
  -2.51618843e+00  -2.14628982e+00
  -2.38703254e+00  -2.05315649e+00
  -2.26242825e+00  -1.95771128e+00
  -2.14239596e+00  -1.86003280e+00
  -2.02696100e+00  -1.76020303e+00
  -1.91615362e+00  -1.65830380e+00
  -1.81000889e+00  -1.55441326e+00
  -1.70856756e+00  -1.44860255e+00
  -1.61187733e+00  -1.34093272e+00
  -1.51999430e+00  -1.23145130e+00
  -1.43298501e+00  -1.12018930e+00
  -1.35092838e+00  -1.00715800e+00
  -1.27391855e+00  -8.92345628e-01
  -1.20206996e+00  -7.75714891e-01
  -1.13552569e+00  -6.57201166e-01
  -1.07446838e+00  -5.36710357e-01
  -1.01912726e+00  -4.14114251e-01
  -9.69773921e-01  -2.89240214e-01
  -9.26704956e-01  -1.61858500e-01
  -9.02387489e-01  -7.50673012e-02
  -8.91386862e-01  -3.11463226e-02
  -2.65895875e+00  -1.94333712e+00
  -2.61674501e+00  -1.91218510e+00
  -2.53386402e+00  -1.84910651e+00
  -2.41418505e+00  -1.75222121e+00
  -2.29916489e+00  -1.65312813e+00
  -2.18882596e+00  -1.55188809e+00
  -2.08319820e+00  -1.44855995e+00
  -1.98231874e+00  -1.34319733e+00
  -1.88623256e+00  -1.23584563e+00
  -1.79499366e+00  -1.12653911e+00
  -1.70866665e+00  -1.01529772e+00
  -1.62732956e+00  -9.02124767e-01
  -1.55107708e+00  -7.87004218e-01
  -1.48002554e+00  -6.69898138e-01
  -1.41431789e+00  -5.50744453e-01
  -1.35412615e+00  -4.29452734e-01
  -1.29964782e+00  -3.05897464e-01
  -1.25109594e+00  -1.79909270e-01
  -1.20869371e+00  -5.12690065e-02
  -1.17269337e+00   8.02902849e-02
  -1.14342907e+00   2.15071979e-01
  -1.12873619e+00   3.07298859e-01
  -1.12269650e+00   3.54072950e-01
  -2.67059553e+00  -1.65015395e+00
  -2.63141245e+00  -1.61778900e+00
  -2.55461522e+00  -1.55231147e+00
  -2.44414241e+00  -1.45189665e+00
  -2.33841016e+00  -1.34932647e+00
  -2.23744726e+00  -1.24464094e+00
  -2.14129085e+00  -1.13787357e+00
  -2.04998734e+00  -1.02904876e+00
  -1.96359342e+00  -9.18179040e-01
  -1.88217758e+00  -8.05262223e-01
  -1.80582213e+00  -6.90279496e-01
  -1.73462414e+00  -5.73191937e-01
  -1.66869638e+00  -4.53937367e-01
  -1.60816564e+00  -3.32426782e-01
  -1.55317001e+00  -2.08538873e-01
  -1.50386029e+00  -8.21167883e-02
  -1.46041416e+00   4.70309902e-02
  -1.42306928e+00   1.79124770e-01
  -1.39216140e+00   3.14410693e-01
  -1.36812265e+00   4.53174463e-01
  -1.35140298e+00   5.95781576e-01
  -1.34532603e+00   6.93748639e-01
  -1.34356695e+00   7.43557823e-01
  -2.68554536e+00  -1.35712147e+00
  -2.64931177e+00  -1.32361218e+00
  -2.57843490e+00  -1.25586007e+00
  -2.47689677e+00  -1.15205888e+00
  -2.38016426e+00  -1.04610951e+00
  -2.28827269e+00  -9.38028962e-01
  -2.20126761e+00  -8.27824515e-01
  -2.11920582e+00  -7.15491054e-01
  -2.04215605e+00  -6.01008609e-01
  -1.97020011e+00  -4.84340474e-01
  -1.90343313e+00  -3.65429073e-01
  -1.84196673e+00  -2.44194369e-01
  -1.78593237e+00  -1.20531808e-01
  -1.73549110e+00   5.68991043e-03
  -1.69084933e+00   1.34626755e-01
  -1.65227355e+00   2.66459947e-01
  -1.62008427e+00   4.01404588e-01
  -1.59460636e+00   5.39733315e-01
  -1.57607497e+00   6.81807176e-01
  -1.56458426e+00   8.28087051e-01
  -1.56016887e+00   9.79091093e-01
  -1.56220753e+00   1.08321462e+00
  -1.56466184e+00   1.13620149e+00
  -2.70380714e+00  -1.06427639e+00
  -2.67044525e+00  -1.02966872e+00
  -2.60531622e+00  -9.59720412e-01
  -2.51244732e+00  -8.52613570e-01
  -2.42443273e+00  -7.43325593e-01
  -2.34131654e+00  -6.31849943e-01
  -2.26315472e+00  -5.18167548e-01
  -2.19001442e+00  -4.02244508e-01
  -2.12197556e+00  -2.84030213e-01
  -2.05913229e+00  -1.63453374e-01
  -2.00159791e+00  -4.04229019e-02
  -1.94950601e+00   8.51753089e-02
  -1.90301281e+00   2.13481980e-01
  -1.86228886e+00   3.44666835e-01
  -1.82749389e+00   4.78941463e-01
  -1.79873679e+00   6.16574706e-01
  -1.77605596e+00   7.57900164e-01
  -1.75947443e+00   9.03297009e-01
  -1.74920172e+00   1.05313615e+00
  -1.74586264e+00   1.20773446e+00
  -1.75060763e+00   1.36738246e+00
  -1.75981759e+00   1.47754287e+00
  -1.76585116e+00   1.53373695e+00
  -2.72538200e+00  -7.71657111e-01
  -2.69480321e+00  -7.35976533e-01
  -2.63526039e+00  -6.63875651e-01
  -2.55079353e+00  -5.53493116e-01
  -2.47122015e+00  -4.40862733e-01
  -2.39659443e+00  -3.25954582e-01
  -2.32697918e+00  -2.08723823e-01
  -2.26245079e+00  -8.91089931e-02
  -2.20309976e+00   3.29713850e-02
  -2.14903287e+00   1.57616734e-01
  -2.10036681e+00   2.84952308e-01
  -2.05722707e+00   4.15132462e-01
  -2.01973933e+00   5.48342547e-01
  -1.98803350e+00   6.84808069e-01
  -1.96227906e+00   8.24786856e-01
  -1.94277814e+00   9.68546731e-01
  -1.93007469e+00   1.11634193e+00
  -1.92499358e+00   1.26842278e+00
  -1.92834935e+00   1.42513893e+00
  -1.94034357e+00   1.58711085e+00
  -1.95971574e+00   1.75540395e+00
  -1.97592951e+00   1.87261627e+00
  -1.98476289e+00   1.93255355e+00
  -2.75025905e+00  -4.79299560e-01
  -2.72239267e+00  -4.42559720e-01
  -2.66825830e+00  -3.68318410e-01
  -2.59193611e+00  -2.54653119e-01
  -2.52053845e+00  -1.38645468e-01
  -2.45412100e+00  -2.02415639e-02
  -2.39275725e+00   1.00628251e-01
  -2.33653184e+00   2.24052922e-01
  -2.28554068e+00   3.50138732e-01
  -2.23988478e+00   4.79021309e-01
  -2.19968201e+00   6.10860714e-01
  -2.16507132e+00   7.45840419e-01
  -2.13623946e+00   8.84172620e-01
  -2.11344722e+00   1.02608278e+00
  -2.09702292e+00   1.17181388e+00
  -2.08722868e+00   1.32166736e+00
  -2.08398438e+00   1.47608216e+00
  -2.08650192e+00   1.63572118e+00
  -2.09332076e+00   1.80142695e+00
  -2.10328842e+00   1.97394107e+00
  -2.11798275e+00   2.15329766e+00
  -2.13608772e+00   2.27675463e+00
  -2.14919387e+00   2.33937140e+00
  -2.77844756e+00  -1.87243468e-01
  -2.75319251e+00  -1.49441027e-01
  -2.70431689e+00  -7.30544533e-02
  -2.63588387e+00   4.39277603e-02
  -2.57238580e+00   1.63372247e-01
  -2.51389851e+00   2.85353578e-01
  -2.46049766e+00   4.09965816e-01
  -2.41226891e+00   5.37320299e-01
  -2.36930798e+00   6.67558611e-01
  -2.33174130e+00   8.00835653e-01
  -2.29971542e+00   9.37327445e-01
  -2.27340244e+00   1.07724190e+00
  -2.25296139e+00   1.22080924e+00
  -2.23845466e+00   1.36832111e+00
  -2.22973886e+00   1.52016949e+00
  -2.22649286e+00   1.67684711e+00
  -2.22861297e+00   1.83885099e+00
  -2.23715168e+00   2.00646890e+00
  -2.25562118e+00   2.17953694e+00
  -2.28997256e+00   2.35762559e+00
  -2.34535854e+00   2.54121865e+00
  -2.39029223e+00   2.67043665e+00
  -2.40832805e+00   2.73861020e+00
  -2.80992109e+00   1.04478137e-01
  -2.78723060e+00   1.43345217e-01
  -2.74343046e+00   2.21902848e-01
  -2.68261971e+00   3.42258505e-01
  -2.62677338e+00   4.65210296e-01
  -2.57594626e+00   5.90857418e-01
  -2.53021724e+00   7.19314306e-01
  -2.48968105e+00   8.50723812e-01
  -2.45445868e+00   9.85231765e-01
  -2.42465431e+00   1.12301865e+00
  -2.40035814e+00   1.26430588e+00
  -2.38160260e+00   1.40934065e+00
  -2.36835787e+00   1.55844290e+00
  -2.36062883e+00   1.71197637e+00
  -2.35873947e+00   1.87027252e+00
  -2.36371865e+00   2.03352825e+00
  -2.37733087e+00   2.20180405e+00
  -2.40096320e+00   2.37528694e+00
  -2.43185075e+00   2.55517293e+00
  -2.45693875e+00   2.74498953e+00
  -2.44539207e+00   2.95178886e+00
  -2.38327855e+00   3.10648210e+00
  -2.33297698e+00   3.18848391e+00
  -2.84472019e+00   3.95819810e-01
  -2.82445747e+00   4.35775461e-01
  -2.78558661e+00   5.16535384e-01
  -2.73218324e+00   6.40321914e-01
  -2.68370564e+00   7.66860631e-01
  -2.64024542e+00   8.96264437e-01
  -2.60189173e+00   1.02867406e+00
  -2.56873447e+00   1.16422931e+00
  -2.54081375e+00   1.30312822e+00
  -2.51817818e+00   1.44559747e+00
  -2.50086780e+00   1.59186912e+00
  -2.48899450e+00   1.74223196e+00
  -2.48285945e+00   1.89693792e+00
  -2.48301081e+00   2.05616858e+00
  -2.48993187e+00   2.22008797e+00
  -2.50296615e+00   2.38907680e+00
  -2.51829712e+00   2.56415883e+00
  -2.52632156e+00   2.74760397e+00
  -2.51066745e+00   2.94313272e+00
  -2.45232847e+00   3.15486404e+00
  -2.34412020e+00   3.38391312e+00
  -2.25888097e+00   3.54378115e+00
  -2.22530697e+00   3.62330011e+00
  -2.88275738e+00   6.86759417e-01
  -2.86493369e+00   7.27805098e-01
  -2.83083642e+00   8.10802688e-01
  -2.78450538e+00   9.38102195e-01
  -2.74313186e+00   1.06830603e+00
  -2.70676523e+00   1.20155561e+00
  -2.67544558e+00   1.33799056e+00
  -2.64917956e+00   1.47782666e+00
  -2.62806177e+00   1.62126059e+00
  -2.61219879e+00   1.76847731e+00
  -2.60176377e+00   1.91972064e+00
  -2.59690460e+00   2.07515536e+00
  -2.59740850e+00   2.23497704e+00
  -2.60194769e+00   2.39957991e+00
  -2.60700135e+00   2.56980387e+00
  -2.60587767e+00   2.74716642e+00
  -2.58873596e+00   2.93398828e+00
  -2.54497881e+00   3.13295557e+00
  -2.46880989e+00   3.34589908e+00
  -2.36588613e+00   3.57226280e+00
  -2.25397609e+00   3.80917405e+00
  -2.17381924e+00   3.97430018e+00
  -2.12212095e+00   4.06018602e+00
  -2.92418323e+00   9.77231486e-01
  -2.90858157e+00   1.01940892e+00
  -2.87902273e+00   1.10469994e+00
  -2.83962565e+00   1.23555891e+00
  -2.80508115e+00   1.36949993e+00
  -2.77541171e+00   1.50666009e+00
  -2.75066112e+00   1.64725474e+00
  -2.73100013e+00   1.79141091e+00
  -2.71646436e+00   1.93927855e+00
  -2.70696631e+00   2.09109840e+00
  -2.70197369e+00   2.24701775e+00
  -2.70003749e+00   2.40739520e+00
  -2.69820706e+00   2.57291260e+00
  -2.69169429e+00   2.74467639e+00
  -2.67412105e+00   2.92424011e+00
  -2.63878317e+00   3.11351483e+00
  -2.58102165e+00   3.31425924e+00
  -2.50091743e+00   3.52734888e+00
  -2.40349612e+00   3.75247867e+00
  -2.29346949e+00   3.98883330e+00
  -2.16221307e+00   4.23647623e+00
  -2.05162164e+00   4.40713305e+00
  -1.99682574e+00   4.49119765e+00
  -2.96869937e+00   1.26725213e+00
  -2.95542410e+00   1.31054984e+00
  -2.93043102e+00   1.39813270e+00
  -2.89750034e+00   1.53264326e+00
  -2.86932854e+00   1.67038623e+00
  -2.84604263e+00   1.81155138e+00
  -2.82778191e+00   1.95618263e+00
  -2.81423412e+00   2.10446164e+00
  -2.80478174e+00   2.25667419e+00
  -2.79804412e+00   2.41299100e+00
  -2.79160910e+00   2.57400810e+00
  -2.78191283e+00   2.74058678e+00
  -2.76454315e+00   2.91385530e+00
  -2.73490505e+00   3.09519178e+00
  -2.68931339e+00   3.28613461e+00
  -2.62612138e+00   3.48796651e+00
  -2.54606931e+00   3.70141339e+00
  -2.45052626e+00   3.92675030e+00
  -2.33802320e+00   4.16393576e+00
  -2.20195065e+00   4.41203801e+00
  -2.04073948e+00   4.66661249e+00
  -1.92595421e+00   4.83562734e+00
  -1.86466562e+00   4.92010998e+00
  -3.01685702e+00   1.55668296e+00
  -3.00558679e+00   1.60115169e+00
  -2.98451330e+00   1.69115105e+00
  -2.95787026e+00   1.82931877e+00
  -2.93618848e+00   1.97084249e+00
  -2.91931938e+00   2.11571510e+00
  -2.90635733e+00   2.26424286e+00
  -2.89616616e+00   2.41675086e+00
  -2.88673057e+00   2.57343239e+00
  -2.87530167e+00   2.73515307e+00
  -2.85861036e+00   2.90276942e+00
  -2.83332806e+00   3.07729919e+00
  -2.79649529e+00   3.25998163e+00
  -2.74604831e+00   3.45219172e+00
  -2.68101150e+00   3.65507863e+00
  -2.60095457e+00   3.86955946e+00
  -2.50457475e+00   4.09639977e+00
  -2.38873064e+00   4.33568747e+00
  -2.24986615e+00   4.58558024e+00
  -2.08956014e+00   4.84112519e+00
  -1.91431133e+00   5.09597504e+00
  -1.78447909e+00   5.26268505e+00
  -1.71729118e+00   5.34384582e+00
  -3.06750589e+00   1.84569586e+00
  -3.05838873e+00   1.89131947e+00
  -3.04203937e+00   1.98354743e+00
  -3.02235020e+00   2.12519558e+00
  -3.00693181e+00   2.27011470e+00
  -2.99427676e+00   2.41880022e+00
  -2.98304626e+00   2.57152794e+00
  -2.97091149e+00   2.72852201e+00
  -2.95532678e+00   2.89094880e+00
  -2.93370985e+00   3.05943878e+00
  -2.90369838e+00   3.23494342e+00
  -2.86321221e+00   3.41873558e+00
  -2.81066360e+00   3.61220286e+00
  -2.74475080e+00   3.81655188e+00
  -2.66383330e+00   4.03306259e+00
  -2.56532988e+00   4.26288393e+00
  -2.44621080e+00   4.50587935e+00
  -2.30492401e+00   4.75929946e+00
  -2.14352630e+00   5.01768798e+00
  -1.96544216e+00   5.27490216e+00
  -1.76962587e+00   5.52613152e+00
  -1.63076026e+00   5.68634653e+00
  -1.55985519e+00   5.76454572e+00
  -3.12426339e+00   2.13358682e+00
  -3.11783062e+00   2.18019940e+00
  -3.10622490e+00   2.27460694e+00
  -3.09230976e+00   2.41944264e+00
  -3.07993540e+00   2.56823227e+00
  -3.06796698e+00   2.72106189e+00
  -3.05387451e+00   2.87827978e+00
  -3.03562780e+00   3.04137068e+00
  -3.01127478e+00   3.21047764e+00
  -2.97896007e+00   3.38675425e+00
  -2.93684956e+00   3.57167531e+00
  -2.88332274e+00   3.76669099e+00
  -2.81655293e+00   3.97319209e+00
  -2.73403124e+00   4.19297622e+00
  -2.63268276e+00   4.42742294e+00
  -2.51002592e+00   4.67578257e+00
  -2.36565787e+00   4.93419756e+00
  -2.20160035e+00   5.19659381e+00
  -2.02027116e+00   5.45684290e+00
  -1.82249520e+00   5.71013592e+00
  -1.61228634e+00   5.95241509e+00
  -1.46469691e+00   6.10509050e+00
  -1.38886177e+00   6.17861894e+00
  -3.19001509e+00   2.41956874e+00
  -3.18535619e+00   2.46731293e+00
  -3.17726589e+00   2.56371352e+00
  -3.16551784e+00   2.71252730e+00
  -3.15361543e+00   2.86526344e+00
  -3.13860954e+00   3.02261344e+00
  -3.11925362e+00   3.18629866e+00
  -3.09390895e+00   3.35569387e+00
  -3.06079100e+00   3.53271868e+00
  -3.01804509e+00   3.71902433e+00
  -2.96392521e+00   3.91606060e+00
  -2.89605238e+00   4.12562964e+00
  -2.81124841e+00   4.35025183e+00
  -2.70633254e+00   4.59126602e+00
  -2.57954281e+00   4.84684041e+00
  -2.43136057e+00   5.11184198e+00
  -2.26393641e+00   5.37967371e+00
  -2.07950986e+00   5.64437933e+00
  -1.87969045e+00   5.90140329e+00
  -1.66733514e+00   6.14706130e+00
  -1.44331772e+00   6.37865885e+00
  -1.28712418e+00   6.52207349e+00
  -1.20812413e+00   6.59105679e+00
  -3.26350960e+00   2.70364763e+00
  -3.26036249e+00   2.75235366e+00
  -3.25327705e+00   2.85153065e+00
  -3.24245590e+00   3.00392282e+00
  -3.22744710e+00   3.16136041e+00
  -3.20831280e+00   3.32550885e+00
  -3.18314438e+00   3.49479420e+00
  -3.15000676e+00   3.67281978e+00
  -3.10709102e+00   3.86090244e+00
  -3.05249346e+00   4.06050447e+00
  -2.98310096e+00   4.27436900e+00
  -2.89516045e+00   4.50590635e+00
  -2.78574828e+00   4.75583159e+00
  -2.65406445e+00   5.02060068e+00
  -2.50142655e+00   5.29364684e+00
  -2.33013370e+00   5.56794263e+00
  -2.14224877e+00   5.83769514e+00
  -1.93935914e+00   6.09846748e+00
  -1.72340852e+00   6.34667325e+00
  -1.49542286e+00   6.57965230e+00
  -1.25763801e+00   6.79581154e+00
  -1.09488163e+00   6.92865417e+00
  -1.01256710e+00   6.99194944e+00
  -3.34555975e+00   2.98538489e+00
  -3.34215532e+00   3.03563193e+00
  -3.33647180e+00   3.13676752e+00
  -3.32198480e+00   3.29428607e+00
  -3.30423666e+00   3.45860520e+00
  -3.27987559e+00   3.62735735e+00
  -3.24707192e+00   3.80701804e+00
  -3.20430325e+00   3.99717754e+00
  -3.14919275e+00   4.19993060e+00
  -3.07752369e+00   4.41991489e+00
  -2.98522595e+00   4.66121152e+00
  -2.87019036e+00   4.92278595e+00
  -2.73286985e+00   5.19867182e+00
  -2.57533436e+00   5.48092755e+00
  -2.39990230e+00   5.76243773e+00
  -2.20838723e+00   6.03787667e+00
  -2.00223485e+00   6.30332012e+00
  -1.78310310e+00   6.55586355e+00
  -1.55246540e+00   6.79362073e+00
  -1.31264316e+00   7.01548434e+00
  -1.06576846e+00   7.22008913e+00
  -8.96638212e-01   7.34206127e+00
  -8.11375370e-01   7.39883373e+00
  -3.43512832e+00   3.26480614e+00
  -3.43278931e+00   3.31591455e+00
  -3.42323475e+00   3.42095415e+00
  -3.40813912e+00   3.58493240e+00
  -3.38463012e+00   3.75286347e+00
  -3.35240273e+00   3.93520407e+00
  -3.31019253e+00   4.12720482e+00
  -3.25422333e+00   4.33393876e+00
  -3.17889094e+00   4.56302854e+00
  -3.08057943e+00   4.81793052e+00
  -2.95875963e+00   5.09411170e+00
  -2.81529742e+00   5.38273450e+00
  -2.65274179e+00   5.67501743e+00
  -2.47317735e+00   5.96436844e+00
  -2.27803144e+00   6.24625489e+00
  -2.06844206e+00   6.51734973e+00
  -1.84559530e+00   6.77503999e+00
  -1.61049634e+00   7.01707209e+00
  -1.36425859e+00   7.24075674e+00
  -1.10795664e+00   7.44259605e+00
  -8.43778855e-01   7.61886117e+00
  -6.69473886e-01   7.72330146e+00
  -5.86980013e-01   7.77656180e+00
  -3.53361198e+00   3.54125809e+00
  -3.52777980e+00   3.59489930e+00
  -3.52111286e+00   3.70371195e+00
  -3.49761413e+00   3.87080988e+00
  -3.46665432e+00   4.05698598e+00
  -3.42557765e+00   4.24937499e+00
  -3.36759556e+00   4.46197767e+00
  -3.28626669e+00   4.70520647e+00
  -3.17998787e+00   4.97858504e+00
  -3.05050655e+00   5.27211435e+00
  -2.90085378e+00   5.57449820e+00
  -2.73351696e+00   5.87725893e+00
  -2.55001362e+00   6.17499864e+00
  -2.35122416e+00   6.46409068e+00
  -2.13781754e+00   6.74162908e+00
  -1.91042943e+00   7.00498530e+00
  -1.66968753e+00   7.25155931e+00
  -1.41672511e+00   7.47853487e+00
  -1.15419708e+00   7.68412501e+00
  -8.87992648e-01   7.86965620e+00
  -6.29373497e-01   8.04398169e+00
  -4.67446855e-01   8.15637592e+00
  -3.84224371e-01   8.20324173e+00
  -3.63834750e+00   3.81527225e+00
  -3.63656918e+00   3.87016364e+00
  -3.61864151e+00   3.98040950e+00
  -3.59130400e+00   4.17098874e+00
  -3.55161599e+00   4.36046654e+00
  -3.48868934e+00   4.58397890e+00
  -3.39795338e+00   4.84943425e+00
  -3.28193488e+00   5.14661619e+00
  -3.14462124e+00   5.45924639e+00
  -2.98931301e+00   5.77554939e+00
  -2.81772283e+00   6.08892924e+00
  -2.63054644e+00   6.39558947e+00
  -2.42806219e+00   6.69266532e+00
  -2.21044746e+00   6.97748209e+00
  -1.97788449e+00   7.24738587e+00
  -1.73077767e+00   7.49969634e+00
  -1.47024961e+00   7.73177135e+00
  -1.19862059e+00   7.94177557e+00
  -9.18896922e-01   8.12831549e+00
  -6.31355167e-01   8.28657648e+00
  -3.24236121e-01   8.39438745e+00
  -8.06024343e-02   8.38835701e+00
   6.08903709e-02   8.34920385e+00
  -3.75409715e+00   4.08518303e+00
  -3.74016535e+00   4.14290324e+00
  -3.72975813e+00   4.27427023e+00
  -3.68937604e+00   4.45526903e+00
  -3.61547542e+00   4.70194096e+00
  -3.51136331e+00   5.00106802e+00
  -3.38492042e+00   5.32615327e+00
  -3.24068578e+00   5.65767471e+00
  -3.08079040e+00   5.98717659e+00
  -2.90562751e+00   6.31125044e+00
  -2.71507901e+00   6.62750073e+00
  -2.50889538e+00   6.93349537e+00
  -2.28678035e+00   7.22668458e+00
  -2.04844778e+00   7.50441248e+00
  -1.79384101e+00   7.76383370e+00
  -1.52334702e+00   8.00181353e+00
  -1.23760815e+00   8.21477493e+00
  -9.36546508e-01   8.39727922e+00
  -6.17132098e-01   8.53834705e+00
  -2.73093799e-01   8.61846572e+00
   1.01126599e-01   8.61116301e+00
   3.53442045e-01   8.55634755e+00
   4.60578876e-01   8.53987679e+00
  -3.87068072e+00   4.35376720e+00
  -3.87423654e+00   4.42230925e+00
  -3.83911456e+00   4.52453559e+00
  -3.74381965e+00   4.82187551e+00
  -3.62340274e+00   5.16818601e+00
  -3.48808768e+00   5.52107906e+00
  -3.33896278e+00   5.86868889e+00
  -3.17580557e+00   6.21032863e+00
  -2.99775521e+00   6.54552829e+00
  -2.80417297e+00   6.87232147e+00
  -2.59435256e+00   7.18840339e+00
  -2.36744664e+00   7.49133982e+00
  -2.12254290e+00   7.77840930e+00
  -1.85880727e+00   8.04630297e+00
  -1.57555759e+00   8.29087648e+00
  -1.27200572e+00   8.50657062e+00
  -9.47169068e-01   8.68550368e+00
  -5.99727962e-01   8.81587011e+00
  -2.31040463e-01   8.88423071e+00
   1.51543858e-01   8.87995008e+00
   5.27242268e-01   8.81315554e+00
   7.59843042e-01   8.74202445e+00
   8.87339155e-01   8.68514285e+00
  -3.96828528e+00   4.52601367e+00
  -3.92838337e+00   4.58137589e+00
  -3.85652956e+00   4.81460647e+00
  -3.73490701e+00   5.18386761e+00
  -3.60236393e+00   5.54547682e+00
  -3.45637042e+00   5.90170382e+00
  -3.29644476e+00   6.25339492e+00
  -3.12179429e+00   6.59905839e+00
  -2.93164030e+00   6.93649876e+00
  -2.72490833e+00   7.26378269e+00
  -2.50031951e+00   7.57872588e+00
  -2.25647280e+00   7.87857543e+00
  -1.99191906e+00   8.15975828e+00
  -1.70525657e+00   8.41764308e+00
  -1.39525745e+00   8.64613613e+00
  -1.06131232e+00   8.83729945e+00
  -7.04291162e-01   8.98124773e+00
  -3.28082551e-01   9.06751534e+00
   5.85745138e-02   9.08862624e+00
   4.43914315e-01   9.04365631e+00
   8.14481998e-01   8.94320955e+00
   1.05411077e+00   8.84754643e+00
   1.15829417e+00   8.82557451e+00
  -3.96817433e+00   4.62648569e+00
  -3.93166858e+00   4.75163035e+00
  -3.85507352e+00   5.00087738e+00
  -3.72861262e+00   5.37100183e+00
  -3.58996017e+00   5.73674140e+00
  -3.43832702e+00   6.09730388e+00
  -3.27282221e+00   6.45172693e+00
  -3.09240696e+00   6.79881655e+00
  -2.89588472e+00   7.13707291e+00
  -2.68188799e+00   7.46459084e+00
  -2.44887505e+00   7.77891745e+00
  -2.19515216e+00   8.07685798e+00
  -1.91898105e+00   8.35424035e+00
  -1.61877361e+00   8.60560484e+00
  -1.29353291e+00   8.82392126e+00
  -9.43631589e-01   9.00053165e+00
  -5.71912406e-01   9.12564365e+00
  -1.84802678e-01   9.19008598e+00
   2.07720552e-01   9.18811300e+00
   5.94175050e-01   9.11991004e+00
   9.64756868e-01   8.99152289e+00
   1.19709084e+00   8.87195716e+00
   1.30915090e+00   8.80536743e+00
    </coefs> 
   </Geometry> 
</xml>