<?xml version="1.0" encoding="UTF-8"?>
 <xml> 
   <Geometry type="TensorBSpline2" id="0"> 
   <Basis type="TensorBSplineBasis2"> 
     <Basis type="BSplineBasis" index="0"> 
<KnotVector degree="3">  0.          0.          0.          0.          0.08333333  0.16666667
  0.25        0.33333333  0.41666667  0.5         0.58333333  0.66666667
  0.75        0.83333333  0.91666667  1.          1.          1.          1.         </KnotVector> 
     </Basis> 
     <Basis type="BSplineBasis" index="1"> 
<KnotVector degree="3">  0.          0.          0.          0.          0.02857143  0.05714286
  0.08571429  0.11428571  0.14285714  0.17142857  0.2         0.22857143
  0.25714286  0.28571429  0.31428571  0.34285714  0.37142857  0.4
  0.42857143  0.45714286  0.48571429  0.51428571  0.54285714  0.57142857
  0.6         0.62857143  0.65714286  0.68571429  0.71428571  0.74285714
  0.77142857  0.8         0.82857143  0.85714286  0.88571429  0.91428571
  0.94285714  0.97142857  1.          1.          1.          1.         </KnotVector> 
     </Basis> 
    </Basis> 
    <coefs geoDim="2"> 
-4.54072592 -7.22316241
 -4.34758021 -7.4128298 
 -3.94171952 -7.77233235
 -3.27707977 -8.24130598
 -2.56172645 -8.62892483
 -1.80338695 -8.92420396
 -1.01271798 -9.11747679
 -0.20303421 -9.20162934
  0.61053991 -9.17337432
  1.41249409 -9.03382368
  2.18846014 -8.78831629
  2.92639111 -8.4454093 
  3.61710354 -8.01559187
  4.04185313 -7.6785287 
  4.24465249 -7.49922134
 -4.36880293 -7.10813931
 -4.16539147 -7.29172999
 -3.75282619 -7.62771666
 -3.08391704 -8.06281327
 -2.37203545 -8.41630783
 -1.62367085 -8.68030057
 -0.84990115 -8.84663613
 -0.06302154 -8.91053164
  0.7226818  -8.87114741
  1.49392004 -8.730302  
  2.23673775 -8.49709482
  2.94348748 -8.17651145
  3.59999767 -7.79220183
  4.00992387 -7.49043519
  4.18484942 -7.37108764
 -4.01497325 -6.89312484
 -3.80919471 -7.04866695
 -3.38451332 -7.34289763
 -2.71365938 -7.71284667
 -2.01197097 -8.00497916
 -1.28729975 -8.21321886
 -0.54925832 -8.33371972
  0.19082426 -8.36586147
  0.9218291  -8.31126841
  1.63201279 -8.17712854
  2.31362492 -7.96970222
  2.95574875 -7.70657998
  3.55920154 -7.39639263
  3.92103827 -7.19639362
  4.10261516 -7.10044338
 -3.49740887 -6.55018856
 -3.2856786  -6.67958613
 -2.85685775 -6.91617406
 -2.19524592 -7.20312355
 -1.52036358 -7.41885237
 -0.83917071 -7.56203724
 -0.15986919 -7.63371764
  0.50935163 -7.63689388
  1.16039836 -7.57766455
  1.78721973 -7.46295385
  2.38372887 -7.30413648
  2.94877529 -7.11075062
  3.47792452 -6.9025846 
  3.81364872 -6.76151926
  3.97494555 -6.69661394
 -2.98622562 -6.19783871
 -2.77501151 -6.30111881
 -2.34992096 -6.48747346
 -1.70921671 -6.70382131
 -1.07028671 -6.85777652
 -0.43903181 -6.95197778
  0.17882218 -6.99052388
  0.77798435 -6.97922774
  1.35457163 -6.92456167
  1.90549783 -6.83467963
  2.43024183 -6.71692825
  2.9282311  -6.58136216
  3.40373311 -6.4347209 
  3.70653247 -6.33802792
  3.85762237 -6.28935179
 -2.48462846 -5.83194924
 -2.27639426 -5.91316774
 -1.86266097 -6.05557355
 -1.25251715 -6.21296613
 -0.65705781 -6.31837735
 -0.07994772 -6.37701394
  0.47575251 -6.39483816
  1.00818955 -6.37798356
  1.5164346  -6.33291962
  2.00107716 -6.26540474
  2.46318647 -6.18165731
  2.90585153 -6.0862069 
  3.33160464 -5.98503685
  3.60854323 -5.91507637
  3.74519541 -5.88089317
 -1.99129008 -5.45495108
 -1.79020323 -5.51593343
 -1.39422388 -5.62037726
 -0.82310568 -5.72974047
 -0.27656694 -5.79826857
  0.24420077 -5.83237892
  0.73921487 -5.83814731
  1.20930061 -5.8212022 
  1.65623845 -5.78632954
  2.08221462 -5.73792493
  2.49027402 -5.6792776 
  2.88334941 -5.61377956
  3.26565046 -5.54325663
  3.51542514 -5.49496534
  3.64037152 -5.47030771
 -1.50765418 -5.06575121
 -1.31613777 -5.10964689
 -0.94445165 -5.18211375
 -0.41890244 -5.25376144
  0.07504727 -5.29544998
  0.53930873 -5.31347227
  0.97633279 -5.31307955
  1.38913408 -5.29848177
  1.78086538 -5.27311675
  2.15492573 -5.23952328
  2.51455446 -5.19990638
  2.86332095 -5.15564158
  3.20441044 -5.10831133
  3.42946394 -5.07498428
  3.54177673 -5.05824954
 -1.03279649 -4.66553345
 -0.85507096 -4.69454679
 -0.5124841  -4.74133906
 -0.03783481 -4.78458593
  0.40184005 -4.80772407
  0.81074912 -4.81588434
  1.19325181 -4.81292135
  1.5534849  -4.80170348
  1.89539138 -4.7842708 
  2.22255876 -4.76218705
  2.53844052 -4.73646186
  2.84615528 -4.70800571
  3.148981   -4.67722705
  3.34953267 -4.65565383
  3.45018154 -4.64453823
 -0.56871684 -4.25352147
 -0.4058685  -4.27137873
 -0.09784903 -4.2982741 
  0.32262807 -4.32145729
  0.70774567 -4.33261647
  1.06340653 -4.33529819
  1.39487732 -4.3319658 
  1.70679666 -4.32427183
  2.0031692  -4.31336492
  2.28754963 -4.29996862
  2.56305814 -4.2846323 
  2.83263895 -4.26762998
  3.09896151 -4.24927879
  3.27624818 -4.23614502
  3.36522004 -4.22943889
 -0.11272866 -3.83140641
  0.02993916 -3.83988492
  0.30054398 -3.85290409
  0.6652725  -3.86320329
  0.99662756 -3.86742015
  1.30141703 -3.86767839
  1.58514603 -3.86527721
  1.85231157 -3.86102404
  2.10667447 -3.85539033
  2.35141902 -3.84868089
  2.58935385 -3.84103218
  2.82296641 -3.83255599
  3.05464897 -3.82323252
  3.20930062 -3.81650662
  3.28710836 -3.81298032
  0.32953903 -3.39693666
  0.45431211 -3.40079406
  0.68507965 -3.40534358
  0.99288229 -3.40823349
  1.27181955 -3.40926516
  1.52824407 -3.40927112
  1.76714432 -3.40868967
  1.99252452 -3.40772982
  2.20767055 -3.40649487
  2.41533815 -3.40499183
  2.61788652 -3.40320344
  2.81744153 -3.40105371
  3.01594345 -3.39849386
  3.14887351 -3.39643145
  3.21579106 -3.39531581
  0.76778382 -2.954899  
  0.8672047  -2.95425377
  1.05513154 -2.95387439
  1.30763608 -2.95430965
  1.53639713 -2.95526594
  1.74684949 -2.95670878
  1.94334922 -2.9586086 
  2.12932387 -2.96090548
  2.30750198 -2.96349388
  2.48012702 -2.96626099
  2.64912381 -2.96907543
  2.81619176 -2.97182208
  2.98292193 -2.97436615
  3.09485348 -2.97586438
  3.15128052 -2.97653631
  1.18320697 -2.49713189
  1.26532211 -2.49775159
  1.41567932 -2.49858624
  1.613939   -2.5003049 
  1.7935399  -2.50312389
  1.95960947 -2.50706533
  2.11562361 -2.51196283
  2.26413709 -2.51759761
  2.40718316 -2.52376646
  2.54645651 -2.53028293
  2.68342133 -2.5369886 
  2.81939759 -2.54373288
  2.955606   -2.55038843
  3.04736745 -2.55467292
  3.09368237 -2.55676084
  1.61019874 -2.03958796
  1.66411025 -2.03877917
  1.76728686 -2.03899236
  1.91011944 -2.0429289 
  2.042753   -2.04916178
  2.16708098 -2.05689655
  2.28491984 -2.06563817
  2.39790607 -2.07506802
  2.50746204 -2.08495932
  2.61481694 -2.09514132
  2.72104981 -2.10546989
  2.8271271  -2.11582347
  2.93395218 -2.12608503
  3.00624413 -2.13279831
  3.04280814 -2.13610362
  1.98383508 -1.55318802
  2.02430002 -1.55754692
  2.09920707 -1.56617205
  2.19871025 -1.57900178
  2.28940246 -1.59193723
  2.37412567 -1.60509034
  2.45489142 -1.61849182
  2.53314755 -1.63211731
  2.60998077 -1.64591273
  2.68624532 -1.65980603
  2.76264764 -1.67371896
  2.8398071  -1.68756649
  2.91829352 -1.70126421
  2.97187536 -1.71023388
  2.9990737  -1.71466379
  2.42469124 -1.09337748
  2.43672784 -1.09714286
  2.46125671 -1.10547097
  2.49962422 -1.11981447
  2.53943493 -1.13549131
  2.58056311 -1.15209323
  2.62295108 -1.16930859
  2.66661    -1.18690252
  2.71160334 -1.20469572
  2.75803411 -1.2225502 
  2.80603806 -1.24035523
  2.85578072 -1.25802168
  2.90746061 -1.27547204
  2.94336145 -1.28691811
  2.96172082 -1.29258313
  2.71156163 -0.55629723
  2.71317706 -0.56843271
  2.71714584 -0.59146018
  2.72524708 -0.62309472
  2.73559453 -0.65252322
  2.74827041 -0.6802716 
  2.76331202 -0.70672399
  2.78071167 -0.73215237
  2.80043307 -0.75674393
  2.8224225  -0.780621  
  2.84661954 -0.80385932
  2.87296411 -0.82649796
  2.90140385 -0.84855175
  2.92173691 -0.86286063
  2.93224501 -0.86991456
  2.62206136  0.09951806
  2.63322393  0.07609481
  2.65453606  0.03118558
  2.68384807 -0.03077632
  2.71085156 -0.08774709
  2.73591196 -0.14018492
  2.75939972 -0.18855981
  2.78168406 -0.23332841
  2.80311263 -0.27491734
  2.82400638 -0.31371433
  2.84465289 -0.35006133
  2.86530763 -0.38425619
  2.88619003 -0.4165501 
  2.90038356 -0.43695119
  2.90757028 -0.44689685
  2.65461161  0.70265525
  2.6598113   0.67428253
  2.6706623   0.6193943 
  2.6884054   0.5420333 
  2.70745459  0.46917116
  2.72753213  0.4004949 
  2.74834288  0.33576633
  2.76960369  0.27477983
  2.79108002  0.21733937
  2.81258585  0.16324941
  2.83398783  0.11230851
  2.85519436  0.06431494
  2.87615823  0.01906322
  2.88996922 -0.00941182
  2.89684237 -0.02326084
  2.58914849  1.33173556
  2.60607186  1.29272871
  2.63659824  1.21839667
  2.6744828   1.11619617
  2.7064855   1.02194185
  2.73427544  0.93448408
  2.75913729  0.85289434
  2.78204062  0.77643727
  2.80367659  0.70453319
  2.82453287  0.63672234
  2.84493585  0.57264015
  2.8651032   0.5119855 
  2.88515868  0.45451285
  2.8984874   0.41817975
  2.90513444  0.400481  
  2.5381077   1.94398143
  2.55630596  1.89882902
  2.59104843  1.81167452
  2.63892691  1.68986357
  2.68248278  1.57621867
  2.7217652   1.47010665
  2.75705137  1.37089112
  2.7887455   1.27795244
  2.81734639  1.1907049 
  2.84335574  1.10861368
  2.86725848  1.03119302
  2.88948174  0.9580212 
  2.91041916  0.88871821
  2.92375849  0.84487517
  2.93033697  0.82349054
  2.44203095  2.56194764
  2.47491775  2.50741748
  2.5335141   2.40359206
  2.6050124   2.26021231
  2.6649897   2.12733224
  2.71659929  2.00346233
  2.76183043  1.88754459
  2.80199108  1.7787626 
  2.83794676  1.67645633
  2.87035623  1.5800589 
  2.89973155  1.48908152
  2.92652248  1.40307383
  2.95108287  1.3216499 
  2.96616008  1.27018819
  2.97339897  1.24511658
  2.33295896  3.16963258
  2.37263007  3.10630893
  2.44708816  2.98635812
  2.54554339  2.82236181
  2.63047048  2.67084672
  2.70330366  2.52995267
  2.76589283  2.39820627
  2.82000309  2.27453314
  2.86718252  2.15807985
  2.90863936  2.04817592
  2.94535671  1.94424883
  2.97808746  1.8458338 
  3.00750643  1.75248804
  3.02529651  1.69338456
  3.03384153  1.66454612
  2.19410572  3.77900409
  2.25589951  3.70907603
  2.36242518  3.57354294
  2.48981833  3.3858994 
  2.59756168  3.2135599 
  2.6903558   3.05400999
  2.77090143  2.90548963
  2.84098216  2.76644161
  2.90205662  2.63572012
  2.95545853  2.51238487
  3.00229932  2.39572716
  3.04357305  2.2851304 
  3.0800039   2.18014788
  3.10147105  2.11362277
  3.11155439  2.08118309
  2.0321192   4.37126023
  2.0935167   4.28443129
  2.22371379  4.13262596
  2.39920714  3.93042608
  2.5459306   3.74313744
  2.66962966  3.56889467
  2.77479054  3.40574467
  2.86520686  3.25262165
  2.94341679  3.10836343
  3.01131074  2.97212475
  3.07045361  2.84308549
  3.1220941   2.72064614
  3.16746771  2.60417969
  3.19418036  2.53022956
  3.20683141  2.4940851 
  1.87035744  4.99164052
  1.97096011  4.90331368
  2.11669918  4.71791876
  2.30715812  4.47859605
  2.48168265  4.26789084
  2.63534713  4.07585419
  2.76920373  3.89799787
  2.88500558  3.73132779
  2.98538262  3.57435696
  3.07249806  3.4258143 
  3.14810737  3.28495388
  3.21374579  3.15100567
  3.27050079  3.02355004
  3.30322792  2.94252233
  3.31843253  2.90296642
  1.28919023  5.30534181
  1.51212059  5.29898917
  1.84707626  5.210876  
  2.15636533  4.99724555
  2.38921038  4.78053208
  2.58329245  4.57540938
  2.75034298  4.38369868
  2.89553077  4.20399849
  3.02197232  4.03457883
  3.13228332  3.87423895
  3.22868958  3.72177795
  3.31282998  3.57657823
  3.38635076  3.43781824
  3.4288487   3.34946165
  3.44871366  3.30618634
  0.81659689  5.68559488
  0.99531534  5.65159675
  1.39178399  5.60231281
  1.86819637  5.45719485
  2.21419591  5.26344136
  2.48241137  5.06020452
  2.70146687  4.86093495
  2.88696735  4.67063673
  3.04668084  4.48994666
  3.18556238  4.31823285
  3.3067894   4.15486133
  3.41313198  3.99870039
  3.50621268  3.84939417
  3.56086507  3.75372122
  3.58637792  3.70692109
  0.28231924  6.01854114
  0.51486413  6.02970901
  0.92024492  5.99445566
  1.47903802  5.88800923
  1.94391823  5.72802783
  2.30998061  5.53556052
  2.60378459  5.33430389
  2.84578448  5.13532167
  3.05039566  4.94348884
  3.22605978  4.76026031
  3.37879716  4.58525797
  3.51208972  4.41835188
  3.62943313  4.25812339
  3.69782488  4.15584539
  3.73021484  4.10544577
 -0.23259453  6.35739491
 -0.01576187  6.3710583 
  0.43681467  6.38773372
  1.04910508  6.32018474
  1.59890203  6.19171258
  2.06543375  6.01647464
  2.44824837  5.81595772
  2.76315487  5.60828518
  3.02567493  5.40350505
  3.24866227  5.20589808
  3.44039614  5.01736948
  3.6077283   4.83707037
  3.75386056  4.66550497
  3.84034214  4.55530046
  3.88053628  4.50165307
 -0.77001572  6.67302215
 -0.53442034  6.7154489 
 -0.08148309  6.76091385
  0.58510763  6.75249024
  1.20022534  6.6627454 
  1.75349722  6.51220582
  2.23072286  6.31833443
  2.63159255  6.10255917
  2.96677419  5.88128312
  3.2487603   5.66479709
  3.48972482  5.4567805 
  3.69741479  5.25988318
  3.88020641  5.07178635
  3.98654361  4.95360877
  4.03766287  4.89506231
 -1.30680181  6.9830989 
 -1.07699014  7.04007387
 -0.60615703  7.13136144
  0.08469206  7.17640865
  0.75487589  7.1394423 
  1.37982509  7.02436929
  1.94601469  6.84839113
  2.44132819  6.63001158
  2.8636344   6.39115233
  3.22049178  6.14843223
  3.52213799  5.91391349
  3.78155638  5.6902768 
  4.00520793  5.48211727
  4.1388539   5.34947202
  4.20033771  5.28646923
 -1.85563902  7.27323827
 -1.62208624  7.35454745
 -1.15354379  7.4858677 
 -0.43901584  7.59647019
  0.26592478  7.61592286
  0.94941043  7.550161  
  1.59216975  7.405794  
  2.17982218  7.1985801 
  2.70065506  6.9471195 
  3.14950106  6.67498148
  3.53133966  6.40042103
  3.85353071  6.14045285
  4.13313883  5.89492761
  4.292395    5.74770983
  4.3710873   5.67397305
 -2.40775348  7.55979358
 -2.18026552  7.65671446
 -1.71154969  7.8306499 
 -0.98988795  8.00692472
 -0.25808838  8.0922775 
  0.46704503  8.08410592
  1.17207781  7.98675917
  1.84055679  7.80734674
  2.45808469  7.56053093
  3.01309665  7.26371922
  3.49614606  6.94337765
  3.90933633  6.62035078
  4.25228791  6.32623482
  4.4552929   6.1426166 
  4.54481776  6.06094622
 -2.97043638  7.81547108
 -2.74580908  7.94134919
 -2.28628475  8.16141246
 -1.56226797  8.40870329
 -0.8167261   8.56507024
 -0.06043827  8.62436818
  0.69143843  8.58551342
  1.42531906  8.45170142
  2.12702193  8.22944908
  2.78288956  7.93183048
  3.38320281  7.57189054
  3.91290823  7.17933633
  4.37241197  6.77388333
  4.60877076  6.55269361
  4.73174142  6.44025348
 -3.34430197  8.00723653
 -3.13093621  8.11706269
 -2.67804784  8.37140859
 -1.96003715  8.6686251 
 -1.2099745   8.87763236
 -0.44094351  8.98708144
  0.33476718  8.99501792
  1.10253529  8.90071374
  1.84895773  8.70883349
  2.56194611  8.42614773
  3.23006067  8.06502549
  3.84780686  7.63405442
  4.40016178  7.16078817
  4.73009576  6.81966769
  4.84798941  6.69967411
 -3.54046672  8.05010631
 -3.32491178  8.19819326
 -2.87732987  8.47051417
 -2.16239041  8.79715967
 -1.41230828  9.03262198
 -0.63797759  9.16919179
  0.14767233  9.20202931
  0.93068     9.1299014 
  1.69733382  8.95547273
  2.43537066  8.68476021
  3.13481177  8.32625311
  3.78817678  7.88966061
  4.39037868  7.38506854
  4.75562333  7.00977576
  4.92895039  6.81393884
    </coefs> 
   </Geometry> 
</xml>